Workbook

Sheet Overview
A1: AqOne Year 1 Plan: DOST-Funded Pilot Deliverables
A2: What we deliver in the 12-month DOST grant period: building, deployment, a 6-month validation period, training for fishers and MDRRMO, and promotion. All dates follow the start date below.
B3: Status | C3: DRAFT (for team and ASU review)
B4: Owner | C4: Aquanons (Lenard, lead student researcher)
B5: Created / Updated | C5: 2026-09-30
B6: Related | C6: docs/funding/Aquanons_Master_Budget.xlsx, AqOne_Investor_Model.xlsx, AqOne_Handoff_Doreen.md
A7: PROJECT DATES
B8: Official DOST start date (Month 1) | C8: 46388 | E8: ASSUMPTION: January 2027. Change this cell when DOST confirms; every date in the workbook updates.
B9: End of grant period (Month 12) | C9: =EDATE(Overview!$C$8,12)-1 -> 46752
B10: Validation period (Months 7-12) | C10: =TEXT(EDATE(Overview!$C$8,7-1),"mmm d, yyyy")&" to "&TEXT(EOMONTH(Overview!$C$8,12-1),"mmm d, yyyy") -> Jul 1, 2027 to Dec 31, 2027 | E10: Six months of supported SOS operation, measured against the validation protocol.
B11: Grant amount requested | C11: 1705525.4 | E11: From Aquanons_Master_Budget.xlsx (28 Sep 2026). See Budget Notes for costs this plan adds.
A13: THREE PHASES
B14: Phase | C14: Starts | D14: Ends | E14: Goal
B15: 1. Set up and build | C15: =EDATE(Overview!$C$8,1-1) -> 46388 | D15: =EOMONTH(Overview!$C$8,3-1) -> 46477 | E15: Agreements, procurement, firmware, app, dashboard and devices ready; validation protocol approved; community awareness starts.
B16: 2. Deploy, train and commission | C16: =EDATE(Overview!$C$8,4-1) -> 46478 | D16: =EOMONTH(Overview!$C$8,6-1) -> 46568 | E16: Coverage measured, devices installed, MDRRMO and fishers trained, soft launch, SOS acceptance test passed (go-live).
B17: 3. Validation period | C17: =EDATE(Overview!$C$8,7-1) -> 46569 | D17: =EOMONTH(Overview!$C$8,12-1) -> 46752 | E17: Six months of supported SOS operation with scheduled and unannounced drills, surveys, usability tests, refresher training, launch and promotion, Year 2 commitment, final reports and handover.
A19: WORKSTREAMS
B20: Workstream | C20: Items | D20: Lead | E20: What it covers
B21: Setup | C21: =COUNTIF(Deliverables!$B$5:$B$61,B21) -> 3 | D21: Doreen + faculty leader | E21: Agreements, procurement, consent and privacy forms.
B22: Build | C22: =COUNTIF(Deliverables!$B$5:$B$61,B22) -> 5 | D22: Lenard, Daniel, Jade, Arnold | E22: Backend, firmware, app, dashboard, device assembly.
B23: Deploy | C23: =COUNTIF(Deliverables!$B$5:$B$61,B23) -> 2 | D23: Daniel | E23: Installation and onboarding of the 20 boats.
B24: Validation | C24: =COUNTIF(Deliverables!$B$5:$B$61,B24) -> 13 | D24: Lenard | E24: Protocol, coverage, soft launch, acceptance test, usability tests, unannounced and night drills, reviews, AI evaluation.
B25: Training | C25: =COUNTIF(Deliverables!$B$5:$B$61,B25) -> 10 | D25: Doreen (fishers), Arnold (MDRRMO) | E25: Curriculum, SOP, MDRRMO operators, champion fishers, fisher batches, joint exercise, refreshers, LGU technicians.
B26: Promotion | C26: =COUNTIF(Deliverables!$B$5:$B$61,B26) -> 14 | D26: Doreen, KC | E26: Communication kit, Facebook page, barangay assemblies, IEC materials, launch, media, stories, briefings, neighbouring LGUs, results forum.
B27: Operations | C27: =COUNTIF(Deliverables!$B$5:$B$61,B27) -> 2 | D27: Daniel | E27: The six-month validation period and the handover package.
B28: Reporting | C28: =COUNTIF(Deliverables!$B$5:$B$61,B28) -> 6 | D28: Faculty leader | E28: Quarterly reports, cost report, final report.
B29: Year 2 | C29: =COUNTIF(Deliverables!$B$5:$B$61,B29) -> 2 | D29: Doreen, KC | E29: Year 2 proposal and commitment from New Washington.
A31: GATES: STOP-AND-CHECK POINTS
B32: Gate | C32: Deadline | D32: Decided by | E32: If not met
B33: G1 Go/no-go on LGU agreement | C33: =EOMONTH(Overview!$C$8,2-1) -> 46446 | D33: Faculty leader + Lenard | E33: Switch to plan B: ASU-arranged boats, buoys and gateway sites, before installation.
B34: G2 Go-live | C34: =EOMONTH(Overview!$C$8,6-1) -> 46568 | D34: Faculty leader, MDRRMO head, Lenard | E34: Do not go live. Fix, re-test within 4 weeks, and shorten the validation period accordingly.
B35: G3 Investor Milestone 1 | C35: =EOMONTH(Overview!$C$8,12-1) -> 46752 | D35: Investor, from DOST/ASU reports and logs | E35: Investor may decline tranche 1 (₱3M).
A37: TEAM
B38: Person | C38: Role | D38: Hours/week | E38: Main Year 1 responsibilities
B39: Lenard | C39: Lead student researcher: backend, architecture, deployment | D39: 20 | E39: Backend, validation protocol and reviews, SOP, acceptance test, AI evaluation, reports
B40: Daniel | C40: Hardware and buoy firmware | D40: 10 | E40: Procurement, firmware, assembly, coverage, installation, upkeep, LGU technician training
B41: Jade | C41: Flutter application | D41: 10 | E41: App, usability tests, fisher training (app parts)
B42: Arnold | C42: Website dashboard | D42: 10 | E42: Dashboard, MDRRMO operator training, joint exercise
B43: Doreen Kay | C43: Pitching, company branding, business direction | D43: 10 | E43: Promotion lead, fisher training lead, surveys, cost report, Year 2 commitment
B44: KC Condes | C44: Pitching and business development support | D44: 10 | E44: Assemblies, IEC, media, surveys, neighbouring LGUs
B45: Faculty project leader (to be named) | C45: Official DOST project leader | E45: Approvals, procurement, gates, protocol, quarterly reports
B47: Sheets: Deliverables (register) · Calendar (week by week) · Gantt · Training Plan · Validation Plan · Promotion Plan · Monthly Ops (validation period tracker) · Gates · Budget Notes (costs this plan adds). Yellow cells are inputs.

Sheet Deliverables
A1: Deliverables Register
A2: Sorted by due month. Deadline = end of the due month. Filter by Workstream to see one area. Update Status and Date done as work finishes.
A4: ID | B4: Workstream | C4: Deliverable | D4: Starts (M) | E4: Due (M) | F4: Due date | G4: Owner | H4: Done when (pass/fail test) | I4: Proof | J4: Gate / milestone | K4: Status | L4: Date done | M4: Notes
A5: D1 | B5: Build | C5: Backend moved to paid Render plan | D5: 1 | E5: 1 | F5: =EOMONTH(Overview!$C$8,E5-1) -> 46418 | G5: Lenard | H5: Paid database with backups live; staging copy live; uptime monitor on; one backup restore tested. | I5: Render invoice, restore log | K5: Not started
A6: D2 | B6: Setup | C6: All pilot hardware ordered | D6: 1 | E6: 1 | F6: =EOMONTH(Overview!$C$8,E6-1) -> 46418 | G6: Daniel + faculty leader | H6: Every B.1 item ordered through ASU procurement, with quotations attached. | I6: Purchase orders, quotations | K6: Not started
A7: D3 | B7: Setup | C7: Fisher consent form and privacy notice | D7: 1 | E7: 1 | F7: =EOMONTH(Overview!$C$8,E7-1) -> 46418 | G7: Doreen | H7: Consent form and privacy notice approved by the faculty leader, in English and Aklanon. | I7: Approved forms | K7: Not started
A8: P1 | B8: Promotion | C8: Communication kit | D8: 1 | E8: 2 | F8: =EOMONTH(Overview!$C$8,E8-1) -> 46446 | G8: Doreen | H8: Key messages in English, Filipino and Aklanon; logo and brand assets; photo/video consent form; one-page project explainer. | I8: Kit folder | K8: Not started
A9: D4 | B9: Setup | C9: LGU agreement and MDRRMO commitment | D9: 1 | E9: 2 | F9: =EOMONTH(Overview!$C$8,E9-1) -> 46446 | G9: Doreen, KC + faculty leader | H9: Signed MOA or LOI covering host buoys, boat access, 2 gateway sites and permits; MDRRMO agrees to monitor alerts and run drills. | I9: Signed documents | J9: G1 | K9: Not started
A10: D5 | B10: Build | C10: Firmware running on RAK boards | D10: 1 | E10: 3 | F10: =EOMONTH(Overview!$C$8,E10-1) -> 46477 | G10: Daniel | H10: 100 of 100 bench SOS messages delivered pod → gateway → dashboard; pod battery lasts at least 48 h; recharge time measured. | I10: Bench test log | K10: Not started
A11: D6 | B11: Build | C11: Android app ready (Google Play closed testing) | D11: 1 | E11: 3 | F11: =EOMONTH(Overview!$C$8,E11-1) -> 46477 | G11: Jade | H11: SOS works through pod Wi-Fi with no internet; English, Filipino and Aklanon; runs on 5 low-end phones. | I11: Play Console listing, phone test sheet | K11: Not started
A12: D7 | B12: Build | C12: MDRRMO dashboard ready | D12: 1 | E12: 3 | F12: =EOMONTH(Overview!$C$8,E12-1) -> 46477 | G12: Arnold | H12: Operator receives and acknowledges a test SOS within 2 minutes; buoy, gateway and pod health visible. | I12: Screen recording | K12: Not started
A13: V1 | B13: Validation | C13: Validation protocol approved | D13: 2 | E13: 3 | F13: =EOMONTH(Overview!$C$8,E13-1) -> 46477 | G13: Lenard + faculty leader | H13: Written protocol: what we measure, targets, sample sizes, how data is collected, stored and anonymized; approved by the faculty leader. | I13: Signed protocol | K13: Not started
A14: D8 | B14: Build | C14: All devices assembled and bench-tested | D14: 2 | E14: 3 | F14: =EOMONTH(Overview!$C$8,E14-1) -> 46477 | G14: Daniel + all | H14: 3 buoy nodes, 22 pods and 2 gateways built; 72-hour burn-in and splash test passed. | I14: Checklist with photos | K14: Not started
A15: R1 | B15: Reporting | C15: Quarterly report 1 | D15: 3 | E15: 3 | F15: =EOMONTH(Overview!$C$8,E15-1) -> 46477 | G15: Faculty leader, Lenard, Doreen | H15: Technical and financial report submitted to ASU/DOST. | I15: Submitted report | K15: Not started
A16: P8a | B16: Promotion | C16: Stakeholder briefing 1 | D16: 3 | E16: 3 | F16: =EOMONTH(Overview!$C$8,E16-1) -> 46477 | G16: Doreen, Lenard | H16: Progress briefing to LGU, MDRRMO, BFAR and Coast Guard; questions and commitments recorded. | I16: Attendance, notes | K16: Not started
A17: P3 | B17: Promotion | C17: Barangay assemblies in coastal barangays | D17: 3 | E17: 4 | F17: =EOMONTH(Overview!$C$8,E17-1) -> 46507 | G17: Doreen, KC + LGU | H17: At least 4 assemblies held with the LGU; 20 boats signed up with a waitlist; common questions collected for the FAQ. | I17: Attendance, sign-up list | K17: Not started
A18: D9 | B18: Validation | C18: Coverage map | D18: 4 | E18: 4 | F18: =EOMONTH(Overview!$C$8,E18-1) -> 46507 | G18: Daniel + Lenard | H18: Signal measured at 50+ GPS-tagged points by boat; coverage map made; buoy positions confirmed with LGU and Coast Guard. | I18: Coverage map and raw data | K18: Not started
A19: T1 | B19: Training | C19: Training curriculum and trainer guide | D19: 4 | E19: 5 | F19: =EOMONTH(Overview!$C$8,E19-1) -> 46538 | G19: Doreen, Jade | H19: Modules, session plans, pre/post test and competency checklist for fishers and MDRRMO operators. | I19: Curriculum, trainer guide | K19: Not started
A20: D10 | B20: Training | C20: Fisher training materials in Aklanon | D20: 4 | E20: 5 | F20: =EOMONTH(Overview!$C$8,E20-1) -> 46538 | G20: Doreen, KC, Jade | H20: Handouts, picture guide and short videos on SOS, charging and basic checks; reviewed by the fisherfolk association. | I20: Final materials, review notes | K20: Not started
A21: T2 | B21: Training | C21: SOS response procedure (SOP) signed with MDRRMO | D21: 4 | E21: 5 | F21: =EOMONTH(Overview!$C$8,E21-1) -> 46538 | G21: Lenard + faculty leader + MDRRMO | H21: Written SOP: who acknowledges an SOS, target times, escalation to Coast Guard and BFAR, contact tree; signed off by the MDRRMO head. | I21: Signed SOP | J21: G2 | K21: Not started
A22: P4 | B22: Promotion | C22: IEC materials printed and placed | D22: 5 | E22: 5 | F22: =EOMONTH(Overview!$C$8,E22-1) -> 46538 | G22: Doreen, KC | H22: Tarpaulins at the fish landing, port, barangay halls and MDRRMO; flyers in Aklanon distributed at assemblies. | I22: Photos of placement | K22: Not started
A23: D11 | B23: Deploy | C23: Gateways and buoy nodes installed | D23: 5 | E23: 5 | F23: =EOMONTH(Overview!$C$8,E23-1) -> 46538 | G23: Daniel + all | H23: 2 gateways on rooftops and 3 buoy nodes on host buoys, all reporting health for 7 days straight. | I23: Dashboard logs, photos | K23: Not started
A24: T3 | B24: Training | C24: MDRRMO operator training | D24: 6 | E24: 6 | F24: =EOMONTH(Overview!$C$8,E24-1) -> 46568 | G24: Arnold, Lenard | H24: All operators on the duty rota (at least 4) trained; each acknowledges a test SOS on the dashboard within 2 minutes; post-test score 80% or higher. | I24: Attendance, test results | J24: G2 | K24: Not started
A25: T4 | B25: Training | C25: Champion fisher training | D25: 6 | E25: 6 | F25: =EOMONTH(Overview!$C$8,E25-1) -> 46568 | G25: Doreen, Jade, Daniel | H25: 5 respected fishers trained first as peer helpers; each can pair a pod, send SOS, charge and do basic checks, and explain them to others. | I25: Attendance, competency checklist | K25: Not started
A26: V2 | B26: Validation | C26: Soft launch with 5 champion boats | D26: 6 | E26: 6 | F26: =EOMONTH(Overview!$C$8,E26-1) -> 46568 | G26: Lenard, Daniel | H26: 5 boats use pods for 1 week before full rollout; at least 10 test messages each delivered; all issues found are fixed or logged. | I26: Soft-launch log | K26: Not started
A27: V3 | B27: Validation | C27: Usability test round 1 | D27: 6 | E27: 6 | F27: =EOMONTH(Overview!$C$8,E27-1) -> 46568 | G27: Jade | H27: At least 10 fishers each try: pair pod, send SOS, check battery. 90%+ complete each task without help; SOS sent within 60 seconds. | I27: Test sheets, notes | K27: Not started
A28: T5 | B28: Training | C28: Fisher training batches and competency check | D28: 6 | E28: 6 | F28: =EOMONTH(Overview!$C$8,E28-1) -> 46568 | G28: Doreen, KC, Jade + champions | H28: 3 batches covering all 20 boats (1-2 fishers per boat). Every fisher sends an SOS and charges a pod without help before receiving a pod; pre/post test gain recorded. | I28: Attendance, competency sheets | J28: G2 | K28: Not started
A29: D12 | B29: Deploy | C29: 20 boats onboarded | D29: 6 | E29: 6 | F29: =EOMONTH(Overview!$C$8,E29-1) -> 46568 | G29: Doreen, KC, Jade | H29: 20 boats have pods; consent forms signed; pod serial numbers matched to boats in the dashboard. | I29: Consent forms, device register | J29: G2 | K29: Not started
A30: D13 | B30: Validation | C30: SOS acceptance test passed (go-live) | D30: 6 | E30: 6 | F30: =EOMONTH(Overview!$C$8,E30-1) -> 46568 | G30: Lenard, Daniel + MDRRMO | H30: At least 30 drills at 3+ locations; 95%+ reach the dashboard within 2 min; MDRRMO acknowledges within 10 min; gateway power-loss and carrier-loss tests passed. | I30: Drill report | J30: G2, Milestone 1 | K30: Not started
A31: R2 | B31: Reporting | C31: Quarterly report 2 and mid-year review | D31: 6 | E31: 6 | F31: =EOMONTH(Overview!$C$8,E31-1) -> 46568 | G31: Faculty leader, Lenard, Doreen | H31: Technical and financial report submitted; mid-year review held with ASU. | I31: Submitted report | K31: Not started
A32: P8b | B32: Promotion | C32: Stakeholder briefing 2 | D32: 6 | E32: 6 | F32: =EOMONTH(Overview!$C$8,E32-1) -> 46568 | G32: Doreen, Lenard | H32: Go-live readiness briefing to LGU, MDRRMO, BFAR and Coast Guard. | I32: Attendance, notes | K32: Not started
A33: P5 | B33: Promotion | C33: Community launch and demo day | D33: 7 | E33: 7 | F33: =EOMONTH(Overview!$C$8,E33-1) -> 46599 | G33: Doreen, KC + LGU | H33: Public launch with LGU, MDRRMO, Coast Guard, BFAR and ASU; live SOS demonstration; at least 60 attendees. | I33: Program, photos, attendance | K33: Not started
A34: P6 | B34: Promotion | C34: Local media feature | D34: 7 | E34: 8 | F34: =EOMONTH(Overview!$C$8,E34-1) -> 46630 | G34: Doreen + ASU public affairs | H34: Press release issued through ASU; at least 1 local radio or news feature. | I34: Press release, clipping or recording | K34: Not started
A35: V5 | B35: Validation | C35: Night and rough-weather readiness drills | D35: 7 | E35: 8 | F35: =EOMONTH(Overview!$C$8,E35-1) -> 46630 | G35: Daniel, Lenard | H35: At least 3 drills at night and 2 in moderate sea conditions (only when safe), meeting the same targets as D13. | I35: Drill log | K35: Not started
A36: D15 | B36: Validation | C36: Fisher feedback survey 1 | D36: 8 | E36: 8 | F36: =EOMONTH(Overview!$C$8,E36-1) -> 46630 | G36: Doreen, KC | H36: At least 15 of 20 boats surveyed; top issues logged and assigned. | I36: Survey results | K36: Not started
A37: T6 | B37: Training | C37: Joint response exercise with MDRRMO and Coast Guard | D37: 8 | E37: 8 | F37: =EOMONTH(Overview!$C$8,E37-1) -> 46630 | G37: Lenard, Arnold + MDRRMO | H37: Tabletop and field exercise following the SOP end to end; lessons logged and the SOP updated. | I37: Exercise report | K37: Not started
A38: D16 | B38: Year 2 | C38: Year 2 proposal presented to the LGU | D38: 8 | E38: 8 | F38: =EOMONTH(Overview!$C$8,E38-1) -> 46630 | G38: Doreen, KC + Lenard | H38: Proposal presented while the LGU prepares next year's budget (usually mid-year). | I38: Presentation, meeting notes | K38: Not started
A39: V6 | B39: Validation | C39: Mid-pilot validation review | D39: 9 | E39: 9 | F39: =EOMONTH(Overview!$C$8,E39-1) -> 46660 | G39: Lenard + faculty leader + MDRRMO | H39: M7-M8 results compared with the protocol targets; decisions to keep, adjust or stop recorded. | I39: Review minutes | K39: Not started
A40: T7 | B40: Training | C40: Refresher training | D40: 9 | E40: 9 | F40: =EOMONTH(Overview!$C$8,E40-1) -> 46660 | G40: Doreen, Jade, Arnold | H40: All active fishers and MDRRMO operators refreshed; replacement fishers trained; repeated after any major app update. | I40: Attendance | K40: Not started
A41: D17 | B41: Reporting | C41: Actual cost report | D41: 9 | E41: 9 | F41: =EOMONTH(Overview!$C$8,E41-1) -> 46660 | G41: Doreen + Daniel | H41: Real cost of buoy node, pod and gateway vs budget, with variances explained. | I41: Cost report | J41: Milestone 1 | K41: Not started
A42: R3 | B42: Reporting | C42: Quarterly report 3 | D42: 9 | E42: 9 | F42: =EOMONTH(Overview!$C$8,E42-1) -> 46660 | G42: Faculty leader, Lenard, Doreen | H42: Technical and financial report submitted to ASU/DOST. | I42: Submitted report | K42: Not started
A43: P8c | B43: Promotion | C43: Stakeholder briefing 3 | D43: 9 | E43: 9 | F43: =EOMONTH(Overview!$C$8,E43-1) -> 46660 | G43: Doreen, Lenard | H43: Mid-pilot results briefing to LGU, MDRRMO, BFAR and Coast Guard. | I43: Attendance, notes | K43: Not started
A44: D18 | B44: Validation | C44: Fisher feedback survey 2 | D44: 10 | E44: 10 | F44: =EOMONTH(Overview!$C$8,E44-1) -> 46691 | G44: Doreen, KC | H44: Same survey repeated; changes since survey 1 reported. | I44: Survey results | K44: Not started
A45: V7 | B45: Validation | C45: Usability test round 2 | D45: 10 | E45: 10 | F45: =EOMONTH(Overview!$C$8,E45-1) -> 46691 | G45: Jade | H45: At least 15 fishers repeat the round 1 tasks; results compared with round 1. | I45: Test sheets, comparison | K45: Not started
A46: P7 | B46: Promotion | C46: Fisher stories and documentation | D46: 7 | E46: 11 | F46: =EOMONTH(Overview!$C$8,E46-1) -> 46721 | G46: Doreen, KC | H46: Monthly photos and video with consent; at least 3 fisher stories published by end of M11. | I46: Published stories | K46: Not started
A47: D19 | B47: Validation | C47: Experimental AI evaluation report | D47: 9 | E47: 11 | F47: =EOMONTH(Overview!$C$8,E47-1) -> 46721 | G47: Lenard | H47: Squall, drift and catch features tested on pilot data; results reported separately from SOS results. | I47: Evaluation report | K47: Not started
A48: P9 | B48: Promotion | C48: Outreach to neighbouring LGUs | D48: 10 | E48: 11 | F48: =EOMONTH(Overview!$C$8,E48-1) -> 46721 | G48: Doreen, KC + Lenard | H48: Pilot results presented to at least 3 other Aklan coastal LGUs; at least 1 LOI (starts the Year 2 pipeline). | I48: Meeting notes, LOIs | K48: Not started
A49: D20 | B49: Year 2 | C49: Year 2 commitment from New Washington | D49: 10 | E49: 11 | F49: =EOMONTH(Overview!$C$8,E49-1) -> 46721 | G49: Doreen, KC | H49: Paid Year 2 agreement or LOI signed. | I49: Signed document | J49: Milestone 1 | K49: Not started
A50: P2 | B50: Promotion | C50: AqOne Facebook page active | D50: 2 | E50: 12 | F50: =EOMONTH(Overview!$C$8,E50-1) -> 46752 | G50: Doreen, KC | H50: Page live by end of M2; at least 2 posts per week through M12; monthly reach and follower report. | I50: Page link, monthly reports | K50: Not started
A51: D14 | B51: Operations | C51: Six-month validation period (supported SOS operation) | D51: 7 | E51: 12 | F51: =EOMONTH(Overview!$C$8,E51-1) -> 46752 | G51: Daniel (upkeep), Lenard | H51: Every month meets the Monthly Ops targets: uptime, longest outage, drills (including unannounced), inspections, active pods. | I51: 6 monthly ops reports | J51: Milestone 1 | K51: Not started
A52: V4 | B52: Validation | C52: Unannounced drills | D52: 8 | E52: 12 | F52: =EOMONTH(Overview!$C$8,E52-1) -> 46752 | G52: Lenard + faculty leader | H52: At least 1 unannounced SOS drill per month from M8; MDRRMO acknowledges within 10 minutes in 90%+ of them. | I52: Drill log with timestamps | K52: Not started
A53: T8 | B53: Training | C53: Maintenance training for LGU technicians | D53: 11 | E53: 12 | F53: =EOMONTH(Overview!$C$8,E53-1) -> 46752 | G53: Daniel | H53: At least 2 LGU technicians can check health, swap a pod battery and reseal an enclosure unaided. | I53: Competency checklist | K53: Not started
A54: D21 | B54: Operations | C54: Handover package | D54: 12 | E54: 12 | F54: =EOMONTH(Overview!$C$8,E54-1) -> 46752 | G54: Daniel, Arnold + all | H54: Operations manual handed over; MDRRMO and LGU operators trained; plan agreed for who runs AqOne after Year 1. | I54: Manual, handover record | K54: Not started
A55: P10 | B55: Promotion | C55: Pilot results forum | D55: 12 | E55: 12 | F55: =EOMONTH(Overview!$C$8,E55-1) -> 46752 | G55: Doreen, KC + all | H55: Public presentation of pilot results to stakeholders and the community. | I55: Program, attendance | K55: Not started
A56: V8 | B56: Validation | C56: Final validation report | D56: 12 | E56: 12 | F56: =EOMONTH(Overview!$C$8,E56-1) -> 46752 | G56: Lenard + faculty leader | H56: All protocol metrics vs targets with raw data and limitations; feeds the final report. | I56: Validation report | K56: Not started
A57: T9 | B57: Training | C57: Training evaluation report | D57: 12 | E57: 12 | F57: =EOMONTH(Overview!$C$8,E57-1) -> 46752 | G57: Doreen | H57: Attendance, pre/post test results, competency pass rates and feedback for every training. | I57: Evaluation report | K57: Not started
A58: D22 | B58: Reporting | C58: Final report and dataset | D58: 12 | E58: 12 | F58: =EOMONTH(Overview!$C$8,E58-1) -> 46752 | G58: All + faculty leader | H58: Final technical report, anonymized dataset and final drill results submitted. | I58: Final report, dataset | K58: Not started
A59: D23 | B59: Promotion | C59: Conference abstract | D59: 12 | E59: 12 | F59: =EOMONTH(Overview!$C$8,E59-1) -> 46752 | G59: Lenard + faculty leader | H59: Abstract submitted to one national research forum. | I59: Submission receipt | K59: Not started
A60: R4 | B60: Reporting | C60: Quarterly report 4 | D60: 12 | E60: 12 | F60: =EOMONTH(Overview!$C$8,E60-1) -> 46752 | G60: Faculty leader, Lenard, Doreen | H60: Technical and financial report submitted; terminal report and liquidation follow per DOST rules. | I60: Submitted report | K60: Not started
A61: P8d | B61: Promotion | C61: Stakeholder briefing 4 | D61: 12 | E61: 12 | F61: =EOMONTH(Overview!$C$8,E61-1) -> 46752 | G61: Doreen, Lenard | H61: Final results briefing to LGU, MDRRMO, BFAR and Coast Guard. | I61: Attendance, notes | K61: Not started
C63: Progress | D63: =COUNTIF(K5:K61,"Done")&" of "&COUNTA(A5:A61)&" done" -> 0 of 57 done

Sheet Calendar
A1: Week-by-Week Calendar
A2: Month names follow the start date on the Overview sheet. Shaded rows mark alternate months.
A4: Month | B4: Month name | C4: Week | D4: Activity | E4: Owner | F4: Deliverables
A5: M1 | B5: =TEXT(EDATE(Overview!$C$8,1-1),"mmm yyyy") -> Jan 2027 | C5: 1 | D5: Kickoff with the faculty project leader and ASU Research Office; confirm expense, procurement, reimbursement and meal rules; assign owners. | E5: All
A6: M1 | B6: =TEXT(EDATE(Overview!$C$8,1-1),"mmm yyyy") -> Jan 2027 | C6: 1 | D6: Move the backend to paid Render; staging copy, uptime monitoring and a backup restore test. | E6: Lenard | F6: D1
A7: M1 | B7: =TEXT(EDATE(Overview!$C$8,1-1),"mmm yyyy") -> Jan 2027 | C7: 2 | D7: Get quotations for all hardware and submit purchase requests. | E7: Daniel + faculty leader | F7: D2
A8: M1 | B8: =TEXT(EDATE(Overview!$C$8,1-1),"mmm yyyy") -> Jan 2027 | C8: 2 | D8: Courtesy visit to New Washington LGU and MDRRMO; present the project; hand over a draft MOA. | E8: Doreen, KC + faculty leader | F8: D4
A9: M1 | B9: =TEXT(EDATE(Overview!$C$8,1-1),"mmm yyyy") -> Jan 2027 | C9: 3 | D9: Start porting firmware to RAK boards on dev kits. Plan app and dashboard sprints. | E9: Daniel, Jade, Arnold | F9: D5, D6, D7
A10: M1 | B10: =TEXT(EDATE(Overview!$C$8,1-1),"mmm yyyy") -> Jan 2027 | C10: 3-4 | D10: Communication kit: key messages in 3 languages, brand assets, photo/video consent form, one-page explainer. | E10: Doreen | F10: P1
A11: M1 | B11: =TEXT(EDATE(Overview!$C$8,1-1),"mmm yyyy") -> Jan 2027 | C11: 4 | D11: Draft the fisher consent form and privacy notice (Data Privacy Act). | E11: Doreen | F11: D3
A12: M2 | B12: =TEXT(EDATE(Overview!$C$8,2-1),"mmm yyyy") -> Feb 2027 | C12: 1 | D12: Launch the AqOne Facebook page and a 2-posts-per-week content calendar. | E12: Doreen, KC | F12: P2
A13: M2 | B13: =TEXT(EDATE(Overview!$C$8,2-1),"mmm yyyy") -> Feb 2027 | C13: 1-2 | D13: Firmware port continues; first parts arrive; dashboard SOS acknowledgement flow; app pod pairing. | E13: Daniel, Arnold, Jade | F13: D5, D6, D7
A14: M2 | B14: =TEXT(EDATE(Overview!$C$8,2-1),"mmm yyyy") -> Feb 2027 | C14: 2 | D14: Draft the validation protocol: metrics, targets, sample sizes, data handling. | E14: Lenard + faculty leader | F14: V1
A15: M2 | B15: =TEXT(EDATE(Overview!$C$8,2-1),"mmm yyyy") -> Feb 2027 | C15: 3 | D15: With the LGU: pick 2 rooftop gateway sites and 3 host buoys; meet the fisherfolk association. | E15: Doreen, KC, Daniel | F15: D4
A16: M2 | B16: =TEXT(EDATE(Overview!$C$8,2-1),"mmm yyyy") -> Feb 2027 | C16: 4 | D16: MOA/LOI signed. Gate G1 go/no-go; switch to plan B if no agreement. Chase late parts. | E16: Faculty leader, Doreen | F16: D4
A17: M3 | B17: =TEXT(EDATE(Overview!$C$8,3-1),"mmm yyyy") -> Mar 2027 | C17: 1-2 | D17: Assemble 22 pods, 2 gateways and 3 buoy nodes; bench SOS tests; pod battery endurance test. | E17: Daniel + all | F17: D5, D8
A18: M3 | B18: =TEXT(EDATE(Overview!$C$8,3-1),"mmm yyyy") -> Mar 2027 | C18: 2-3 | D18: Barangay assemblies 1 and 2 with the LGU: explain AqOne, sign up boats, collect questions. | E18: Doreen, KC | F18: P3
A19: M3 | B19: =TEXT(EDATE(Overview!$C$8,3-1),"mmm yyyy") -> Mar 2027 | C19: 3 | D19: 72-hour burn-in and splash tests; app closed testing on 5 phones; MDRRMO operator accounts. Validation protocol approved. | E19: Daniel, Jade, Arnold, faculty leader | F19: D6, D7, D8, V1
A20: M3 | B20: =TEXT(EDATE(Overview!$C$8,3-1),"mmm yyyy") -> Mar 2027 | C20: 4 | D20: Quarterly report 1; stakeholder briefing 1 (LGU, MDRRMO, BFAR, Coast Guard). | E20: All + faculty leader | F20: R1, P8a
A21: M4 | B21: =TEXT(EDATE(Overview!$C$8,4-1),"mmm yyyy") -> Apr 2027 | C21: 1-2 | D21: Coverage survey by boat: signal at 50+ GPS-tagged points. | E21: Daniel, Lenard | F21: D9
A22: M4 | B22: =TEXT(EDATE(Overview!$C$8,4-1),"mmm yyyy") -> Apr 2027 | C22: 2 | D22: Barangay assemblies 3 and 4; 20 boats signed up plus a waitlist. | E22: Doreen, KC | F22: P3
A23: M4 | B23: =TEXT(EDATE(Overview!$C$8,4-1),"mmm yyyy") -> Apr 2027 | C23: 3 | D23: Coverage map; confirm buoy positions and permits with the LGU and Coast Guard. | E23: Lenard, Doreen | F23: D9
A24: M4 | B24: =TEXT(EDATE(Overview!$C$8,4-1),"mmm yyyy") -> Apr 2027 | C24: 3-4 | D24: Write the training curriculum, trainer guide, pre/post tests and competency checklist; draft fisher materials in Aklanon. | E24: Doreen, Jade | F24: T1, D10
A25: M4 | B25: =TEXT(EDATE(Overview!$C$8,4-1),"mmm yyyy") -> Apr 2027 | C25: 4 | D25: Draft the SOS response SOP with MDRRMO and the Coast Guard. | E25: Lenard + faculty leader | F25: T2
A26: M5 | B26: =TEXT(EDATE(Overview!$C$8,5-1),"mmm yyyy") -> May 2027 | C26: 1 | D26: Install both gateways on the rooftops. | E26: Daniel + all | F26: D11
A27: M5 | B27: =TEXT(EDATE(Overview!$C$8,5-1),"mmm yyyy") -> May 2027 | C27: 2 | D27: MDRRMO head signs off the SOP. | E27: Lenard + faculty leader | F27: T2
A28: M5 | B28: =TEXT(EDATE(Overview!$C$8,5-1),"mmm yyyy") -> May 2027 | C28: 2-3 | D28: Install the 3 buoy nodes on host buoys (sea trips). | E28: Daniel + all | F28: D11
A29: M5 | B29: =TEXT(EDATE(Overview!$C$8,5-1),"mmm yyyy") -> May 2027 | C29: 3 | D29: Print and place IEC materials: tarpaulins at the fish landing, port, barangay halls, MDRRMO; flyers. | E29: Doreen, KC | F29: P4
A30: M5 | B30: =TEXT(EDATE(Overview!$C$8,5-1),"mmm yyyy") -> May 2027 | C30: 4 | D30: 7-day health check of all installed devices; fisherfolk association reviews training materials; finalize curriculum. | E30: Lenard, Doreen, Jade | F30: D10, D11, T1
A31: M6 | B31: =TEXT(EDATE(Overview!$C$8,6-1),"mmm yyyy") -> Jun 2027 | C31: 1 | D31: MDRRMO operator training (full day). Champion fisher training (5 fishers). Soft launch with the 5 champion boats. | E31: Arnold, Lenard, Doreen, Jade, Daniel | F31: T3, T4, V2
A32: M6 | B32: =TEXT(EDATE(Overview!$C$8,6-1),"mmm yyyy") -> Jun 2027 | C32: 1-2 | D32: Usability test round 1 with 10+ fishers. | E32: Jade | F32: V3
A33: M6 | B33: =TEXT(EDATE(Overview!$C$8,6-1),"mmm yyyy") -> Jun 2027 | C33: 2-3 | D33: Fisher training batches 1-3 with champion helpers; competency check; pods handed over; consent forms signed. | E33: Doreen, KC, Jade + champions | F33: T5, D12
A34: M6 | B34: =TEXT(EDATE(Overview!$C$8,6-1),"mmm yyyy") -> Jun 2027 | C34: 3 | D34: SOS acceptance test: 30+ drills at 3+ locations; gateway power-loss and carrier-loss tests. | E34: Lenard, Daniel + MDRRMO | F34: D13
A35: M6 | B35: =TEXT(EDATE(Overview!$C$8,6-1),"mmm yyyy") -> Jun 2027 | C35: 4 | D35: Gate G2 go-live decision. Quarterly report 2, mid-year review, stakeholder briefing 2. | E35: All + faculty leader | F35: R2, P8b
A36: M7 | B36: =TEXT(EDATE(Overview!$C$8,7-1),"mmm yyyy") -> Jul 2027 | C36: 1 | D36: Community launch and demo day with LGU, MDRRMO, Coast Guard, BFAR and ASU; live SOS demo. | E36: Doreen, KC + LGU | F36: P5
A37: M7 | B37: =TEXT(EDATE(Overview!$C$8,7-1),"mmm yyyy") -> Jul 2027 | C37: 1-2 | D37: Press release through ASU; local radio or news feature. | E37: Doreen + ASU public affairs | F37: P6
A38: M7 | B38: =TEXT(EDATE(Overview!$C$8,7-1),"mmm yyyy") -> Jul 2027 | C38: 2-4 | D38: Validation period begins: weekly check-ins, night and rough-weather drills (when safe), experimental AI data collection. | E38: Lenard, Daniel | F38: D14, V5, D19
A39: M7 | B39: =TEXT(EDATE(Overview!$C$8,7-1),"mmm yyyy") -> Jul 2027 | C39: Monthly | D39: Every month M7-M12: 5+ SOS drills, 1 inspection trip (plus checks after bad weather), uptime report, incident log, 2 Facebook posts per week, photos and video with consent. | E39: Daniel, Lenard, Doreen | F39: D14, P2, P7
A40: M8 | B40: =TEXT(EDATE(Overview!$C$8,8-1),"mmm yyyy") -> Aug 2027 | C40: 1 | D40: First unannounced drill (then at least 1 per month to M12). | E40: Lenard + faculty leader | F40: V4
A41: M8 | B41: =TEXT(EDATE(Overview!$C$8,8-1),"mmm yyyy") -> Aug 2027 | C41: 1-2 | D41: Fisher feedback survey 1; app and firmware fixes from the results. Finish night and rough-weather drills. | E41: Doreen, KC, Jade, Daniel | F41: D15, V5
A42: M8 | B42: =TEXT(EDATE(Overview!$C$8,8-1),"mmm yyyy") -> Aug 2027 | C42: 2 | D42: Joint response exercise with MDRRMO and the Coast Guard (tabletop and field); update the SOP. | E42: Lenard, Arnold + MDRRMO | F42: T6
A43: M8 | B43: =TEXT(EDATE(Overview!$C$8,8-1),"mmm yyyy") -> Aug 2027 | C43: 3-4 | D43: Present the Year 2 proposal to the LGU during its budget preparation. | E43: Doreen, KC + Lenard | F43: D16
A44: M9 | B44: =TEXT(EDATE(Overview!$C$8,9-1),"mmm yyyy") -> Sep 2027 | C44: 1 | D44: Mid-pilot validation review against the protocol; keep, adjust or stop decisions. | E44: Lenard + faculty leader + MDRRMO | F44: V6
A45: M9 | B45: =TEXT(EDATE(Overview!$C$8,9-1),"mmm yyyy") -> Sep 2027 | C45: 2 | D45: Refresher training for fishers and MDRRMO operators; train any replacement fishers. | E45: Doreen, Jade, Arnold | F45: T7
A46: M9 | B46: =TEXT(EDATE(Overview!$C$8,9-1),"mmm yyyy") -> Sep 2027 | C46: 1-3 | D46: Compile the real cost of each device vs budget. | E46: Doreen, Daniel | F46: D17
A47: M9 | B47: =TEXT(EDATE(Overview!$C$8,9-1),"mmm yyyy") -> Sep 2027 | C47: 4 | D47: Quarterly report 3; stakeholder briefing 3. | E47: All + faculty leader | F47: R3, P8c
A48: M10 | B48: =TEXT(EDATE(Overview!$C$8,10-1),"mmm yyyy") -> Oct 2027 | C48: 1-2 | D48: Fisher feedback survey 2; usability test round 2 with 15+ fishers. | E48: Doreen, KC, Jade | F48: D18, V7
A49: M10 | B49: =TEXT(EDATE(Overview!$C$8,10-1),"mmm yyyy") -> Oct 2027 | C49: 3-4 | D49: Present pilot results to 3+ neighbouring Aklan coastal LGUs; aim for at least 1 LOI. | E49: Doreen, KC + Lenard | F49: P9
A50: M10 | B50: =TEXT(EDATE(Overview!$C$8,10-1),"mmm yyyy") -> Oct 2027 | C50: 3-4 | D50: Analyze the experimental AI features; draft the Year 2 agreement with the LGU. | E50: Lenard, Doreen | F50: D19, D20
A51: M11 | B51: =TEXT(EDATE(Overview!$C$8,11-1),"mmm yyyy") -> Nov 2027 | C51: 1-2 | D51: Finish the AI evaluation report (separate from SOS results). | E51: Lenard | F51: D19
A52: M11 | B52: =TEXT(EDATE(Overview!$C$8,11-1),"mmm yyyy") -> Nov 2027 | C52: 2-4 | D52: Maintenance training for 2+ LGU technicians begins. | E52: Daniel | F52: T8
A53: M11 | B53: =TEXT(EDATE(Overview!$C$8,11-1),"mmm yyyy") -> Nov 2027 | C53: 3-4 | D53: Year 2 agreement or LOI signed; draft the operations manual; publish the third fisher story. | E53: Doreen, KC, Daniel | F53: D20, D21, P7
A54: M12 | B54: =TEXT(EDATE(Overview!$C$8,12-1),"mmm yyyy") -> Dec 2027 | C54: 1-2 | D54: Complete technician and operator training; hand over the operations manual; agree who runs AqOne after Year 1. | E54: Daniel, Arnold + all | F54: T8, D21
A55: M12 | B55: =TEXT(EDATE(Overview!$C$8,12-1),"mmm yyyy") -> Dec 2027 | C55: 2 | D55: Pilot results forum for stakeholders and the community. | E55: Doreen, KC + all | F55: P10
A56: M12 | B56: =TEXT(EDATE(Overview!$C$8,12-1),"mmm yyyy") -> Dec 2027 | C56: 3 | D56: Final drills; freeze and anonymize the dataset; final validation report; training evaluation report. | E56: Lenard, Daniel, Doreen | F56: V8, T9, D22
A57: M12 | B57: =TEXT(EDATE(Overview!$C$8,12-1),"mmm yyyy") -> Dec 2027 | C57: 4 | D57: Final report, conference abstract, quarterly report 4, stakeholder briefing 4. Investor Milestone 1 check. | E57: All + faculty leader | F57: D22, D23, R4, P8d

Sheet Gantt
A1: 12-Month Gantt
A2: Bars show when each deliverable is worked on. Change Start/End months to move a bar.
E3: 1 | F3: 2 | G3: 3 | H3: 4 | I3: 5 | J3: 6 | K3: 7 | L3: 8 | M3: 9 | N3: 10 | O3: 11 | P3: 12
A4: Workstream | B4: Deliverable | C4: Start | D4: End | E4: M1 | F4: M2 | G4: M3 | H4: M4 | I4: M5 | J4: M6 | K4: M7 | L4: M8 | M4: M9 | N4: M10 | O4: M11 | P4: M12
E5: =TEXT(EDATE(Overview!$C$8,1-1),"mmm") -> Jan | F5: =TEXT(EDATE(Overview!$C$8,2-1),"mmm") -> Feb | G5: =TEXT(EDATE(Overview!$C$8,3-1),"mmm") -> Mar | H5: =TEXT(EDATE(Overview!$C$8,4-1),"mmm") -> Apr | I5: =TEXT(EDATE(Overview!$C$8,5-1),"mmm") -> May | J5: =TEXT(EDATE(Overview!$C$8,6-1),"mmm") -> Jun | K5: =TEXT(EDATE(Overview!$C$8,7-1),"mmm") -> Jul | L5: =TEXT(EDATE(Overview!$C$8,8-1),"mmm") -> Aug | M5: =TEXT(EDATE(Overview!$C$8,9-1),"mmm") -> Sep | N5: =TEXT(EDATE(Overview!$C$8,10-1),"mmm") -> Oct | O5: =TEXT(EDATE(Overview!$C$8,11-1),"mmm") -> Nov | P5: =TEXT(EDATE(Overview!$C$8,12-1),"mmm") -> Dec
A6: Setup | B6: D2 All pilot hardware ordered | C6: 1 | D6: 1 | E6: =IF(AND(E$3>=$C6,E$3<=$D6),1,"") -> 1 | F6: =IF(AND(F$3>=$C6,F$3<=$D6),1,"") | G6: =IF(AND(G$3>=$C6,G$3<=$D6),1,"") | H6: =IF(AND(H$3>=$C6,H$3<=$D6),1,"") | I6: =IF(AND(I$3>=$C6,I$3<=$D6),1,"") | J6: =IF(AND(J$3>=$C6,J$3<=$D6),1,"") | K6: =IF(AND(K$3>=$C6,K$3<=$D6),1,"") | L6: =IF(AND(L$3>=$C6,L$3<=$D6),1,"") | ... P6: =IF(AND(P$3>=$C6,P$3<=$D6),1,"")
B7: D3 Fisher consent form and privacy notice | C7: 1 | D7: 1 | E7: =IF(AND(E$3>=$C7,E$3<=$D7),1,"") -> 1 | F7: =IF(AND(F$3>=$C7,F$3<=$D7),1,"") | G7: =IF(AND(G$3>=$C7,G$3<=$D7),1,"") | H7: =IF(AND(H$3>=$C7,H$3<=$D7),1,"") | I7: =IF(AND(I$3>=$C7,I$3<=$D7),1,"") | J7: =IF(AND(J$3>=$C7,J$3<=$D7),1,"") | K7: =IF(AND(K$3>=$C7,K$3<=$D7),1,"") | L7: =IF(AND(L$3>=$C7,L$3<=$D7),1,"") | ... P7: =IF(AND(P$3>=$C7,P$3<=$D7),1,"")
B8: D4 LGU agreement and MDRRMO commitment | C8: 1 | D8: 2 | E8: =IF(AND(E$3>=$C8,E$3<=$D8),1,"") -> 1 | F8: =IF(AND(F$3>=$C8,F$3<=$D8),1,"") -> 1 | G8: =IF(AND(G$3>=$C8,G$3<=$D8),1,"") | H8: =IF(AND(H$3>=$C8,H$3<=$D8),1,"") | I8: =IF(AND(I$3>=$C8,I$3<=$D8),1,"") | J8: =IF(AND(J$3>=$C8,J$3<=$D8),1,"") | K8: =IF(AND(K$3>=$C8,K$3<=$D8),1,"") | L8: =IF(AND(L$3>=$C8,L$3<=$D8),1,"") | ... P8: =IF(AND(P$3>=$C8,P$3<=$D8),1,"")
A9: Build | B9: D1 Backend moved to paid Render plan | C9: 1 | D9: 1 | E9: =IF(AND(E$3>=$C9,E$3<=$D9),1,"") -> 1 | F9: =IF(AND(F$3>=$C9,F$3<=$D9),1,"") | G9: =IF(AND(G$3>=$C9,G$3<=$D9),1,"") | H9: =IF(AND(H$3>=$C9,H$3<=$D9),1,"") | I9: =IF(AND(I$3>=$C9,I$3<=$D9),1,"") | J9: =IF(AND(J$3>=$C9,J$3<=$D9),1,"") | K9: =IF(AND(K$3>=$C9,K$3<=$D9),1,"") | L9: =IF(AND(L$3>=$C9,L$3<=$D9),1,"") | ... P9: =IF(AND(P$3>=$C9,P$3<=$D9),1,"")
B10: D5 Firmware running on RAK boards | C10: 1 | D10: 3 | E10: =IF(AND(E$3>=$C10,E$3<=$D10),1,"") -> 1 | F10: =IF(AND(F$3>=$C10,F$3<=$D10),1,"") -> 1 | G10: =IF(AND(G$3>=$C10,G$3<=$D10),1,"") -> 1 | H10: =IF(AND(H$3>=$C10,H$3<=$D10),1,"") | I10: =IF(AND(I$3>=$C10,I$3<=$D10),1,"") | J10: =IF(AND(J$3>=$C10,J$3<=$D10),1,"") | K10: =IF(AND(K$3>=$C10,K$3<=$D10),1,"") | L10: =IF(AND(L$3>=$C10,L$3<=$D10),1,"") | ... P10: =IF(AND(P$3>=$C10,P$3<=$D10),1,"")
B11: D6 Android app ready (Google Play closed testing) | C11: 1 | D11: 3 | E11: =IF(AND(E$3>=$C11,E$3<=$D11),1,"") -> 1 | F11: =IF(AND(F$3>=$C11,F$3<=$D11),1,"") -> 1 | G11: =IF(AND(G$3>=$C11,G$3<=$D11),1,"") -> 1 | H11: =IF(AND(H$3>=$C11,H$3<=$D11),1,"") | I11: =IF(AND(I$3>=$C11,I$3<=$D11),1,"") | J11: =IF(AND(J$3>=$C11,J$3<=$D11),1,"") | K11: =IF(AND(K$3>=$C11,K$3<=$D11),1,"") | L11: =IF(AND(L$3>=$C11,L$3<=$D11),1,"") | ... P11: =IF(AND(P$3>=$C11,P$3<=$D11),1,"")
B12: D7 MDRRMO dashboard ready | C12: 1 | D12: 3 | E12: =IF(AND(E$3>=$C12,E$3<=$D12),1,"") -> 1 | F12: =IF(AND(F$3>=$C12,F$3<=$D12),1,"") -> 1 | G12: =IF(AND(G$3>=$C12,G$3<=$D12),1,"") -> 1 | H12: =IF(AND(H$3>=$C12,H$3<=$D12),1,"") | I12: =IF(AND(I$3>=$C12,I$3<=$D12),1,"") | J12: =IF(AND(J$3>=$C12,J$3<=$D12),1,"") | K12: =IF(AND(K$3>=$C12,K$3<=$D12),1,"") | L12: =IF(AND(L$3>=$C12,L$3<=$D12),1,"") | ... P12: =IF(AND(P$3>=$C12,P$3<=$D12),1,"")
B13: D8 All devices assembled and bench-tested | C13: 2 | D13: 3 | E13: =IF(AND(E$3>=$C13,E$3<=$D13),1,"") | F13: =IF(AND(F$3>=$C13,F$3<=$D13),1,"") -> 1 | G13: =IF(AND(G$3>=$C13,G$3<=$D13),1,"") -> 1 | H13: =IF(AND(H$3>=$C13,H$3<=$D13),1,"") | I13: =IF(AND(I$3>=$C13,I$3<=$D13),1,"") | J13: =IF(AND(J$3>=$C13,J$3<=$D13),1,"") | K13: =IF(AND(K$3>=$C13,K$3<=$D13),1,"") | L13: =IF(AND(L$3>=$C13,L$3<=$D13),1,"") | ... P13: =IF(AND(P$3>=$C13,P$3<=$D13),1,"")
A14: Deploy | B14: D11 Gateways and buoy nodes installed | C14: 5 | D14: 5 | E14: =IF(AND(E$3>=$C14,E$3<=$D14),1,"") | F14: =IF(AND(F$3>=$C14,F$3<=$D14),1,"") | G14: =IF(AND(G$3>=$C14,G$3<=$D14),1,"") | H14: =IF(AND(H$3>=$C14,H$3<=$D14),1,"") | I14: =IF(AND(I$3>=$C14,I$3<=$D14),1,"") -> 1 | J14: =IF(AND(J$3>=$C14,J$3<=$D14),1,"") | K14: =IF(AND(K$3>=$C14,K$3<=$D14),1,"") | L14: =IF(AND(L$3>=$C14,L$3<=$D14),1,"") | ... P14: =IF(AND(P$3>=$C14,P$3<=$D14),1,"")
B15: D12 20 boats onboarded | C15: 6 | D15: 6 | E15: =IF(AND(E$3>=$C15,E$3<=$D15),1,"") | F15: =IF(AND(F$3>=$C15,F$3<=$D15),1,"") | G15: =IF(AND(G$3>=$C15,G$3<=$D15),1,"") | H15: =IF(AND(H$3>=$C15,H$3<=$D15),1,"") | I15: =IF(AND(I$3>=$C15,I$3<=$D15),1,"") | J15: =IF(AND(J$3>=$C15,J$3<=$D15),1,"") -> 1 | K15: =IF(AND(K$3>=$C15,K$3<=$D15),1,"") | L15: =IF(AND(L$3>=$C15,L$3<=$D15),1,"") | ... P15: =IF(AND(P$3>=$C15,P$3<=$D15),1,"")
A16: Validation | B16: V1 Validation protocol approved | C16: 2 | D16: 3 | E16: =IF(AND(E$3>=$C16,E$3<=$D16),1,"") | F16: =IF(AND(F$3>=$C16,F$3<=$D16),1,"") -> 1 | G16: =IF(AND(G$3>=$C16,G$3<=$D16),1,"") -> 1 | H16: =IF(AND(H$3>=$C16,H$3<=$D16),1,"") | I16: =IF(AND(I$3>=$C16,I$3<=$D16),1,"") | J16: =IF(AND(J$3>=$C16,J$3<=$D16),1,"") | K16: =IF(AND(K$3>=$C16,K$3<=$D16),1,"") | L16: =IF(AND(L$3>=$C16,L$3<=$D16),1,"") | ... P16: =IF(AND(P$3>=$C16,P$3<=$D16),1,"")
B17: D9 Coverage map | C17: 4 | D17: 4 | E17: =IF(AND(E$3>=$C17,E$3<=$D17),1,"") | F17: =IF(AND(F$3>=$C17,F$3<=$D17),1,"") | G17: =IF(AND(G$3>=$C17,G$3<=$D17),1,"") | H17: =IF(AND(H$3>=$C17,H$3<=$D17),1,"") -> 1 | I17: =IF(AND(I$3>=$C17,I$3<=$D17),1,"") | J17: =IF(AND(J$3>=$C17,J$3<=$D17),1,"") | K17: =IF(AND(K$3>=$C17,K$3<=$D17),1,"") | L17: =IF(AND(L$3>=$C17,L$3<=$D17),1,"") | ... P17: =IF(AND(P$3>=$C17,P$3<=$D17),1,"")
B18: V2 Soft launch with 5 champion boats | C18: 6 | D18: 6 | E18: =IF(AND(E$3>=$C18,E$3<=$D18),1,"") | F18: =IF(AND(F$3>=$C18,F$3<=$D18),1,"") | G18: =IF(AND(G$3>=$C18,G$3<=$D18),1,"") | H18: =IF(AND(H$3>=$C18,H$3<=$D18),1,"") | I18: =IF(AND(I$3>=$C18,I$3<=$D18),1,"") | J18: =IF(AND(J$3>=$C18,J$3<=$D18),1,"") -> 1 | K18: =IF(AND(K$3>=$C18,K$3<=$D18),1,"") | L18: =IF(AND(L$3>=$C18,L$3<=$D18),1,"") | ... P18: =IF(AND(P$3>=$C18,P$3<=$D18),1,"")
B19: V3 Usability test round 1 | C19: 6 | D19: 6 | E19: =IF(AND(E$3>=$C19,E$3<=$D19),1,"") | F19: =IF(AND(F$3>=$C19,F$3<=$D19),1,"") | G19: =IF(AND(G$3>=$C19,G$3<=$D19),1,"") | H19: =IF(AND(H$3>=$C19,H$3<=$D19),1,"") | I19: =IF(AND(I$3>=$C19,I$3<=$D19),1,"") | J19: =IF(AND(J$3>=$C19,J$3<=$D19),1,"") -> 1 | K19: =IF(AND(K$3>=$C19,K$3<=$D19),1,"") | L19: =IF(AND(L$3>=$C19,L$3<=$D19),1,"") | ... P19: =IF(AND(P$3>=$C19,P$3<=$D19),1,"")
B20: D13 SOS acceptance test passed (go-live) | C20: 6 | D20: 6 | E20: =IF(AND(E$3>=$C20,E$3<=$D20),1,"") | F20: =IF(AND(F$3>=$C20,F$3<=$D20),1,"") | G20: =IF(AND(G$3>=$C20,G$3<=$D20),1,"") | H20: =IF(AND(H$3>=$C20,H$3<=$D20),1,"") | I20: =IF(AND(I$3>=$C20,I$3<=$D20),1,"") | J20: =IF(AND(J$3>=$C20,J$3<=$D20),1,"") -> 1 | K20: =IF(AND(K$3>=$C20,K$3<=$D20),1,"") | L20: =IF(AND(L$3>=$C20,L$3<=$D20),1,"") | ... P20: =IF(AND(P$3>=$C20,P$3<=$D20),1,"")
B21: V5 Night and rough-weather readiness drills | C21: 7 | D21: 8 | E21: =IF(AND(E$3>=$C21,E$3<=$D21),1,"") | F21: =IF(AND(F$3>=$C21,F$3<=$D21),1,"") | G21: =IF(AND(G$3>=$C21,G$3<=$D21),1,"") | H21: =IF(AND(H$3>=$C21,H$3<=$D21),1,"") | I21: =IF(AND(I$3>=$C21,I$3<=$D21),1,"") | J21: =IF(AND(J$3>=$C21,J$3<=$D21),1,"") | K21: =IF(AND(K$3>=$C21,K$3<=$D21),1,"") -> 1 | L21: =IF(AND(L$3>=$C21,L$3<=$D21),1,"") -> 1 | ... P21: =IF(AND(P$3>=$C21,P$3<=$D21),1,"")
B22: D15 Fisher feedback survey 1 | C22: 8 | D22: 8 | E22: =IF(AND(E$3>=$C22,E$3<=$D22),1,"") | F22: =IF(AND(F$3>=$C22,F$3<=$D22),1,"") | G22: =IF(AND(G$3>=$C22,G$3<=$D22),1,"") | H22: =IF(AND(H$3>=$C22,H$3<=$D22),1,"") | I22: =IF(AND(I$3>=$C22,I$3<=$D22),1,"") | J22: =IF(AND(J$3>=$C22,J$3<=$D22),1,"") | K22: =IF(AND(K$3>=$C22,K$3<=$D22),1,"") | L22: =IF(AND(L$3>=$C22,L$3<=$D22),1,"") -> 1 | ... P22: =IF(AND(P$3>=$C22,P$3<=$D22),1,"")
B23: V4 Unannounced drills | C23: 8 | D23: 12 | E23: =IF(AND(E$3>=$C23,E$3<=$D23),1,"") | F23: =IF(AND(F$3>=$C23,F$3<=$D23),1,"") | G23: =IF(AND(G$3>=$C23,G$3<=$D23),1,"") | H23: =IF(AND(H$3>=$C23,H$3<=$D23),1,"") | I23: =IF(AND(I$3>=$C23,I$3<=$D23),1,"") | J23: =IF(AND(J$3>=$C23,J$3<=$D23),1,"") | K23: =IF(AND(K$3>=$C23,K$3<=$D23),1,"") | L23: =IF(AND(L$3>=$C23,L$3<=$D23),1,"") -> 1 | ... P23: =IF(AND(P$3>=$C23,P$3<=$D23),1,"") -> 1
B24: V6 Mid-pilot validation review | C24: 9 | D24: 9 | E24: =IF(AND(E$3>=$C24,E$3<=$D24),1,"") | F24: =IF(AND(F$3>=$C24,F$3<=$D24),1,"") | G24: =IF(AND(G$3>=$C24,G$3<=$D24),1,"") | H24: =IF(AND(H$3>=$C24,H$3<=$D24),1,"") | I24: =IF(AND(I$3>=$C24,I$3<=$D24),1,"") | J24: =IF(AND(J$3>=$C24,J$3<=$D24),1,"") | K24: =IF(AND(K$3>=$C24,K$3<=$D24),1,"") | L24: =IF(AND(L$3>=$C24,L$3<=$D24),1,"") | ... P24: =IF(AND(P$3>=$C24,P$3<=$D24),1,"")
B25: D19 Experimental AI evaluation report | C25: 9 | D25: 11 | E25: =IF(AND(E$3>=$C25,E$3<=$D25),1,"") | F25: =IF(AND(F$3>=$C25,F$3<=$D25),1,"") | G25: =IF(AND(G$3>=$C25,G$3<=$D25),1,"") | H25: =IF(AND(H$3>=$C25,H$3<=$D25),1,"") | I25: =IF(AND(I$3>=$C25,I$3<=$D25),1,"") | J25: =IF(AND(J$3>=$C25,J$3<=$D25),1,"") | K25: =IF(AND(K$3>=$C25,K$3<=$D25),1,"") | L25: =IF(AND(L$3>=$C25,L$3<=$D25),1,"") | ... P25: =IF(AND(P$3>=$C25,P$3<=$D25),1,"")
B26: D18 Fisher feedback survey 2 | C26: 10 | D26: 10 | E26: =IF(AND(E$3>=$C26,E$3<=$D26),1,"") | F26: =IF(AND(F$3>=$C26,F$3<=$D26),1,"") | G26: =IF(AND(G$3>=$C26,G$3<=$D26),1,"") | H26: =IF(AND(H$3>=$C26,H$3<=$D26),1,"") | I26: =IF(AND(I$3>=$C26,I$3<=$D26),1,"") | J26: =IF(AND(J$3>=$C26,J$3<=$D26),1,"") | K26: =IF(AND(K$3>=$C26,K$3<=$D26),1,"") | L26: =IF(AND(L$3>=$C26,L$3<=$D26),1,"") | ... P26: =IF(AND(P$3>=$C26,P$3<=$D26),1,"")
B27: V7 Usability test round 2 | C27: 10 | D27: 10 | E27: =IF(AND(E$3>=$C27,E$3<=$D27),1,"") | F27: =IF(AND(F$3>=$C27,F$3<=$D27),1,"") | G27: =IF(AND(G$3>=$C27,G$3<=$D27),1,"") | H27: =IF(AND(H$3>=$C27,H$3<=$D27),1,"") | I27: =IF(AND(I$3>=$C27,I$3<=$D27),1,"") | J27: =IF(AND(J$3>=$C27,J$3<=$D27),1,"") | K27: =IF(AND(K$3>=$C27,K$3<=$D27),1,"") | L27: =IF(AND(L$3>=$C27,L$3<=$D27),1,"") | ... P27: =IF(AND(P$3>=$C27,P$3<=$D27),1,"")
B28: V8 Final validation report | C28: 12 | D28: 12 | E28: =IF(AND(E$3>=$C28,E$3<=$D28),1,"") | F28: =IF(AND(F$3>=$C28,F$3<=$D28),1,"") | G28: =IF(AND(G$3>=$C28,G$3<=$D28),1,"") | H28: =IF(AND(H$3>=$C28,H$3<=$D28),1,"") | I28: =IF(AND(I$3>=$C28,I$3<=$D28),1,"") | J28: =IF(AND(J$3>=$C28,J$3<=$D28),1,"") | K28: =IF(AND(K$3>=$C28,K$3<=$D28),1,"") | L28: =IF(AND(L$3>=$C28,L$3<=$D28),1,"") | ... P28: =IF(AND(P$3>=$C28,P$3<=$D28),1,"") -> 1
A29: Training | B29: T1 Training curriculum and trainer guide | C29: 4 | D29: 5 | E29: =IF(AND(E$3>=$C29,E$3<=$D29),1,"") | F29: =IF(AND(F$3>=$C29,F$3<=$D29),1,"") | G29: =IF(AND(G$3>=$C29,G$3<=$D29),1,"") | H29: =IF(AND(H$3>=$C29,H$3<=$D29),1,"") -> 1 | I29: =IF(AND(I$3>=$C29,I$3<=$D29),1,"") -> 1 | J29: =IF(AND(J$3>=$C29,J$3<=$D29),1,"") | K29: =IF(AND(K$3>=$C29,K$3<=$D29),1,"") | L29: =IF(AND(L$3>=$C29,L$3<=$D29),1,"") | ... P29: =IF(AND(P$3>=$C29,P$3<=$D29),1,"")
B30: D10 Fisher training materials in Aklanon | C30: 4 | D30: 5 | E30: =IF(AND(E$3>=$C30,E$3<=$D30),1,"") | F30: =IF(AND(F$3>=$C30,F$3<=$D30),1,"") | G30: =IF(AND(G$3>=$C30,G$3<=$D30),1,"") | H30: =IF(AND(H$3>=$C30,H$3<=$D30),1,"") -> 1 | I30: =IF(AND(I$3>=$C30,I$3<=$D30),1,"") -> 1 | J30: =IF(AND(J$3>=$C30,J$3<=$D30),1,"") | K30: =IF(AND(K$3>=$C30,K$3<=$D30),1,"") | L30: =IF(AND(L$3>=$C30,L$3<=$D30),1,"") | ... P30: =IF(AND(P$3>=$C30,P$3<=$D30),1,"")
B31: T2 SOS response procedure (SOP) signed with MDRRMO | C31: 4 | D31: 5 | E31: =IF(AND(E$3>=$C31,E$3<=$D31),1,"") | F31: =IF(AND(F$3>=$C31,F$3<=$D31),1,"") | G31: =IF(AND(G$3>=$C31,G$3<=$D31),1,"") | H31: =IF(AND(H$3>=$C31,H$3<=$D31),1,"") -> 1 | I31: =IF(AND(I$3>=$C31,I$3<=$D31),1,"") -> 1 | J31: =IF(AND(J$3>=$C31,J$3<=$D31),1,"") | K31: =IF(AND(K$3>=$C31,K$3<=$D31),1,"") | L31: =IF(AND(L$3>=$C31,L$3<=$D31),1,"") | ... P31: =IF(AND(P$3>=$C31,P$3<=$D31),1,"")
B32: T3 MDRRMO operator training | C32: 6 | D32: 6 | E32: =IF(AND(E$3>=$C32,E$3<=$D32),1,"") | F32: =IF(AND(F$3>=$C32,F$3<=$D32),1,"") | G32: =IF(AND(G$3>=$C32,G$3<=$D32),1,"") | H32: =IF(AND(H$3>=$C32,H$3<=$D32),1,"") | I32: =IF(AND(I$3>=$C32,I$3<=$D32),1,"") | J32: =IF(AND(J$3>=$C32,J$3<=$D32),1,"") -> 1 | K32: =IF(AND(K$3>=$C32,K$3<=$D32),1,"") | L32: =IF(AND(L$3>=$C32,L$3<=$D32),1,"") | ... P32: =IF(AND(P$3>=$C32,P$3<=$D32),1,"")
B33: T4 Champion fisher training | C33: 6 | D33: 6 | E33: =IF(AND(E$3>=$C33,E$3<=$D33),1,"") | F33: =IF(AND(F$3>=$C33,F$3<=$D33),1,"") | G33: =IF(AND(G$3>=$C33,G$3<=$D33),1,"") | H33: =IF(AND(H$3>=$C33,H$3<=$D33),1,"") | I33: =IF(AND(I$3>=$C33,I$3<=$D33),1,"") | J33: =IF(AND(J$3>=$C33,J$3<=$D33),1,"") -> 1 | K33: =IF(AND(K$3>=$C33,K$3<=$D33),1,"") | L33: =IF(AND(L$3>=$C33,L$3<=$D33),1,"") | ... P33: =IF(AND(P$3>=$C33,P$3<=$D33),1,"")
B34: T5 Fisher training batches and competency check | C34: 6 | D34: 6 | E34: =IF(AND(E$3>=$C34,E$3<=$D34),1,"") | F34: =IF(AND(F$3>=$C34,F$3<=$D34),1,"") | G34: =IF(AND(G$3>=$C34,G$3<=$D34),1,"") | H34: =IF(AND(H$3>=$C34,H$3<=$D34),1,"") | I34: =IF(AND(I$3>=$C34,I$3<=$D34),1,"") | J34: =IF(AND(J$3>=$C34,J$3<=$D34),1,"") -> 1 | K34: =IF(AND(K$3>=$C34,K$3<=$D34),1,"") | L34: =IF(AND(L$3>=$C34,L$3<=$D34),1,"") | ... P34: =IF(AND(P$3>=$C34,P$3<=$D34),1,"")
B35: T6 Joint response exercise with MDRRMO and Coast Guard | C35: 8 | D35: 8 | E35: =IF(AND(E$3>=$C35,E$3<=$D35),1,"") | F35: =IF(AND(F$3>=$C35,F$3<=$D35),1,"") | G35: =IF(AND(G$3>=$C35,G$3<=$D35),1,"") | H35: =IF(AND(H$3>=$C35,H$3<=$D35),1,"") | I35: =IF(AND(I$3>=$C35,I$3<=$D35),1,"") | J35: =IF(AND(J$3>=$C35,J$3<=$D35),1,"") | K35: =IF(AND(K$3>=$C35,K$3<=$D35),1,"") | L35: =IF(AND(L$3>=$C35,L$3<=$D35),1,"") -> 1 | ... P35: =IF(AND(P$3>=$C35,P$3<=$D35),1,"")
B36: T7 Refresher training | C36: 9 | D36: 9 | E36: =IF(AND(E$3>=$C36,E$3<=$D36),1,"") | F36: =IF(AND(F$3>=$C36,F$3<=$D36),1,"") | G36: =IF(AND(G$3>=$C36,G$3<=$D36),1,"") | H36: =IF(AND(H$3>=$C36,H$3<=$D36),1,"") | I36: =IF(AND(I$3>=$C36,I$3<=$D36),1,"") | J36: =IF(AND(J$3>=$C36,J$3<=$D36),1,"") | K36: =IF(AND(K$3>=$C36,K$3<=$D36),1,"") | L36: =IF(AND(L$3>=$C36,L$3<=$D36),1,"") | ... P36: =IF(AND(P$3>=$C36,P$3<=$D36),1,"")
B37: T8 Maintenance training for LGU technicians | C37: 11 | D37: 12 | E37: =IF(AND(E$3>=$C37,E$3<=$D37),1,"") | F37: =IF(AND(F$3>=$C37,F$3<=$D37),1,"") | G37: =IF(AND(G$3>=$C37,G$3<=$D37),1,"") | H37: =IF(AND(H$3>=$C37,H$3<=$D37),1,"") | I37: =IF(AND(I$3>=$C37,I$3<=$D37),1,"") | J37: =IF(AND(J$3>=$C37,J$3<=$D37),1,"") | K37: =IF(AND(K$3>=$C37,K$3<=$D37),1,"") | L37: =IF(AND(L$3>=$C37,L$3<=$D37),1,"") | ... P37: =IF(AND(P$3>=$C37,P$3<=$D37),1,"") -> 1
B38: T9 Training evaluation report | C38: 12 | D38: 12 | E38: =IF(AND(E$3>=$C38,E$3<=$D38),1,"") | F38: =IF(AND(F$3>=$C38,F$3<=$D38),1,"") | G38: =IF(AND(G$3>=$C38,G$3<=$D38),1,"") | H38: =IF(AND(H$3>=$C38,H$3<=$D38),1,"") | I38: =IF(AND(I$3>=$C38,I$3<=$D38),1,"") | J38: =IF(AND(J$3>=$C38,J$3<=$D38),1,"") | K38: =IF(AND(K$3>=$C38,K$3<=$D38),1,"") | L38: =IF(AND(L$3>=$C38,L$3<=$D38),1,"") | ... P38: =IF(AND(P$3>=$C38,P$3<=$D38),1,"") -> 1
A39: Promotion | B39: P1 Communication kit | C39: 1 | D39: 2 | E39: =IF(AND(E$3>=$C39,E$3<=$D39),1,"") -> 1 | F39: =IF(AND(F$3>=$C39,F$3<=$D39),1,"") -> 1 | G39: =IF(AND(G$3>=$C39,G$3<=$D39),1,"") | H39: =IF(AND(H$3>=$C39,H$3<=$D39),1,"") | I39: =IF(AND(I$3>=$C39,I$3<=$D39),1,"") | J39: =IF(AND(J$3>=$C39,J$3<=$D39),1,"") | K39: =IF(AND(K$3>=$C39,K$3<=$D39),1,"") | L39: =IF(AND(L$3>=$C39,L$3<=$D39),1,"") | ... P39: =IF(AND(P$3>=$C39,P$3<=$D39),1,"")
B40: P2 AqOne Facebook page active | C40: 2 | D40: 12 | E40: =IF(AND(E$3>=$C40,E$3<=$D40),1,"") | F40: =IF(AND(F$3>=$C40,F$3<=$D40),1,"") -> 1 | G40: =IF(AND(G$3>=$C40,G$3<=$D40),1,"") -> 1 | H40: =IF(AND(H$3>=$C40,H$3<=$D40),1,"") -> 1 | I40: =IF(AND(I$3>=$C40,I$3<=$D40),1,"") -> 1 | J40: =IF(AND(J$3>=$C40,J$3<=$D40),1,"") -> 1 | K40: =IF(AND(K$3>=$C40,K$3<=$D40),1,"") -> 1 | L40: =IF(AND(L$3>=$C40,L$3<=$D40),1,"") -> 1 | ... P40: =IF(AND(P$3>=$C40,P$3<=$D40),1,"") -> 1
B41: P8a Stakeholder briefing 1 | C41: 3 | D41: 3 | E41: =IF(AND(E$3>=$C41,E$3<=$D41),1,"") | F41: =IF(AND(F$3>=$C41,F$3<=$D41),1,"") | G41: =IF(AND(G$3>=$C41,G$3<=$D41),1,"") -> 1 | H41: =IF(AND(H$3>=$C41,H$3<=$D41),1,"") | I41: =IF(AND(I$3>=$C41,I$3<=$D41),1,"") | J41: =IF(AND(J$3>=$C41,J$3<=$D41),1,"") | K41: =IF(AND(K$3>=$C41,K$3<=$D41),1,"") | L41: =IF(AND(L$3>=$C41,L$3<=$D41),1,"") | ... P41: =IF(AND(P$3>=$C41,P$3<=$D41),1,"")
B42: P3 Barangay assemblies in coastal barangays | C42: 3 | D42: 4 | E42: =IF(AND(E$3>=$C42,E$3<=$D42),1,"") | F42: =IF(AND(F$3>=$C42,F$3<=$D42),1,"") | G42: =IF(AND(G$3>=$C42,G$3<=$D42),1,"") -> 1 | H42: =IF(AND(H$3>=$C42,H$3<=$D42),1,"") -> 1 | I42: =IF(AND(I$3>=$C42,I$3<=$D42),1,"") | J42: =IF(AND(J$3>=$C42,J$3<=$D42),1,"") | K42: =IF(AND(K$3>=$C42,K$3<=$D42),1,"") | L42: =IF(AND(L$3>=$C42,L$3<=$D42),1,"") | ... P42: =IF(AND(P$3>=$C42,P$3<=$D42),1,"")
B43: P4 IEC materials printed and placed | C43: 5 | D43: 5 | E43: =IF(AND(E$3>=$C43,E$3<=$D43),1,"") | F43: =IF(AND(F$3>=$C43,F$3<=$D43),1,"") | G43: =IF(AND(G$3>=$C43,G$3<=$D43),1,"") | H43: =IF(AND(H$3>=$C43,H$3<=$D43),1,"") | I43: =IF(AND(I$3>=$C43,I$3<=$D43),1,"") -> 1 | J43: =IF(AND(J$3>=$C43,J$3<=$D43),1,"") | K43: =IF(AND(K$3>=$C43,K$3<=$D43),1,"") | L43: =IF(AND(L$3>=$C43,L$3<=$D43),1,"") | ... P43: =IF(AND(P$3>=$C43,P$3<=$D43),1,"")
B44: P8b Stakeholder briefing 2 | C44: 6 | D44: 6 | E44: =IF(AND(E$3>=$C44,E$3<=$D44),1,"") | F44: =IF(AND(F$3>=$C44,F$3<=$D44),1,"") | G44: =IF(AND(G$3>=$C44,G$3<=$D44),1,"") | H44: =IF(AND(H$3>=$C44,H$3<=$D44),1,"") | I44: =IF(AND(I$3>=$C44,I$3<=$D44),1,"") | J44: =IF(AND(J$3>=$C44,J$3<=$D44),1,"") -> 1 | K44: =IF(AND(K$3>=$C44,K$3<=$D44),1,"") | L44: =IF(AND(L$3>=$C44,L$3<=$D44),1,"") | ... P44: =IF(AND(P$3>=$C44,P$3<=$D44),1,"")
B45: P5 Community launch and demo day | C45: 7 | D45: 7 | E45: =IF(AND(E$3>=$C45,E$3<=$D45),1,"") | F45: =IF(AND(F$3>=$C45,F$3<=$D45),1,"") | G45: =IF(AND(G$3>=$C45,G$3<=$D45),1,"") | H45: =IF(AND(H$3>=$C45,H$3<=$D45),1,"") | I45: =IF(AND(I$3>=$C45,I$3<=$D45),1,"") | J45: =IF(AND(J$3>=$C45,J$3<=$D45),1,"") | K45: =IF(AND(K$3>=$C45,K$3<=$D45),1,"") -> 1 | L45: =IF(AND(L$3>=$C45,L$3<=$D45),1,"") | ... P45: =IF(AND(P$3>=$C45,P$3<=$D45),1,"")
B46: P6 Local media feature | C46: 7 | D46: 8 | E46: =IF(AND(E$3>=$C46,E$3<=$D46),1,"") | F46: =IF(AND(F$3>=$C46,F$3<=$D46),1,"") | G46: =IF(AND(G$3>=$C46,G$3<=$D46),1,"") | H46: =IF(AND(H$3>=$C46,H$3<=$D46),1,"") | I46: =IF(AND(I$3>=$C46,I$3<=$D46),1,"") | J46: =IF(AND(J$3>=$C46,J$3<=$D46),1,"") | K46: =IF(AND(K$3>=$C46,K$3<=$D46),1,"") -> 1 | L46: =IF(AND(L$3>=$C46,L$3<=$D46),1,"") -> 1 | ... P46: =IF(AND(P$3>=$C46,P$3<=$D46),1,"")
B47: P7 Fisher stories and documentation | C47: 7 | D47: 11 | E47: =IF(AND(E$3>=$C47,E$3<=$D47),1,"") | F47: =IF(AND(F$3>=$C47,F$3<=$D47),1,"") | G47: =IF(AND(G$3>=$C47,G$3<=$D47),1,"") | H47: =IF(AND(H$3>=$C47,H$3<=$D47),1,"") | I47: =IF(AND(I$3>=$C47,I$3<=$D47),1,"") | J47: =IF(AND(J$3>=$C47,J$3<=$D47),1,"") | K47: =IF(AND(K$3>=$C47,K$3<=$D47),1,"") -> 1 | L47: =IF(AND(L$3>=$C47,L$3<=$D47),1,"") -> 1 | ... P47: =IF(AND(P$3>=$C47,P$3<=$D47),1,"")
B48: P8c Stakeholder briefing 3 | C48: 9 | D48: 9 | E48: =IF(AND(E$3>=$C48,E$3<=$D48),1,"") | F48: =IF(AND(F$3>=$C48,F$3<=$D48),1,"") | G48: =IF(AND(G$3>=$C48,G$3<=$D48),1,"") | H48: =IF(AND(H$3>=$C48,H$3<=$D48),1,"") | I48: =IF(AND(I$3>=$C48,I$3<=$D48),1,"") | J48: =IF(AND(J$3>=$C48,J$3<=$D48),1,"") | K48: =IF(AND(K$3>=$C48,K$3<=$D48),1,"") | L48: =IF(AND(L$3>=$C48,L$3<=$D48),1,"") | ... P48: =IF(AND(P$3>=$C48,P$3<=$D48),1,"")
B49: P9 Outreach to neighbouring LGUs | C49: 10 | D49: 11 | E49: =IF(AND(E$3>=$C49,E$3<=$D49),1,"") | F49: =IF(AND(F$3>=$C49,F$3<=$D49),1,"") | G49: =IF(AND(G$3>=$C49,G$3<=$D49),1,"") | H49: =IF(AND(H$3>=$C49,H$3<=$D49),1,"") | I49: =IF(AND(I$3>=$C49,I$3<=$D49),1,"") | J49: =IF(AND(J$3>=$C49,J$3<=$D49),1,"") | K49: =IF(AND(K$3>=$C49,K$3<=$D49),1,"") | L49: =IF(AND(L$3>=$C49,L$3<=$D49),1,"") | ... P49: =IF(AND(P$3>=$C49,P$3<=$D49),1,"")
B50: P10 Pilot results forum | C50: 12 | D50: 12 | E50: =IF(AND(E$3>=$C50,E$3<=$D50),1,"") | F50: =IF(AND(F$3>=$C50,F$3<=$D50),1,"") | G50: =IF(AND(G$3>=$C50,G$3<=$D50),1,"") | H50: =IF(AND(H$3>=$C50,H$3<=$D50),1,"") | I50: =IF(AND(I$3>=$C50,I$3<=$D50),1,"") | J50: =IF(AND(J$3>=$C50,J$3<=$D50),1,"") | K50: =IF(AND(K$3>=$C50,K$3<=$D50),1,"") | L50: =IF(AND(L$3>=$C50,L$3<=$D50),1,"") | ... P50: =IF(AND(P$3>=$C50,P$3<=$D50),1,"") -> 1
B51: D23 Conference abstract | C51: 12 | D51: 12 | E51: =IF(AND(E$3>=$C51,E$3<=$D51),1,"") | F51: =IF(AND(F$3>=$C51,F$3<=$D51),1,"") | G51: =IF(AND(G$3>=$C51,G$3<=$D51),1,"") | H51: =IF(AND(H$3>=$C51,H$3<=$D51),1,"") | I51: =IF(AND(I$3>=$C51,I$3<=$D51),1,"") | J51: =IF(AND(J$3>=$C51,J$3<=$D51),1,"") | K51: =IF(AND(K$3>=$C51,K$3<=$D51),1,"") | L51: =IF(AND(L$3>=$C51,L$3<=$D51),1,"") | ... P51: =IF(AND(P$3>=$C51,P$3<=$D51),1,"") -> 1
B52: P8d Stakeholder briefing 4 | C52: 12 | D52: 12 | E52: =IF(AND(E$3>=$C52,E$3<=$D52),1,"") | F52: =IF(AND(F$3>=$C52,F$3<=$D52),1,"") | G52: =IF(AND(G$3>=$C52,G$3<=$D52),1,"") | H52: =IF(AND(H$3>=$C52,H$3<=$D52),1,"") | I52: =IF(AND(I$3>=$C52,I$3<=$D52),1,"") | J52: =IF(AND(J$3>=$C52,J$3<=$D52),1,"") | K52: =IF(AND(K$3>=$C52,K$3<=$D52),1,"") | L52: =IF(AND(L$3>=$C52,L$3<=$D52),1,"") | ... P52: =IF(AND(P$3>=$C52,P$3<=$D52),1,"") -> 1
A53: Operations | B53: D14 Six-month validation period (supported SOS operation) | C53: 7 | D53: 12 | E53: =IF(AND(E$3>=$C53,E$3<=$D53),1,"") | F53: =IF(AND(F$3>=$C53,F$3<=$D53),1,"") | G53: =IF(AND(G$3>=$C53,G$3<=$D53),1,"") | H53: =IF(AND(H$3>=$C53,H$3<=$D53),1,"") | I53: =IF(AND(I$3>=$C53,I$3<=$D53),1,"") | J53: =IF(AND(J$3>=$C53,J$3<=$D53),1,"") | K53: =IF(AND(K$3>=$C53,K$3<=$D53),1,"") -> 1 | L53: =IF(AND(L$3>=$C53,L$3<=$D53),1,"") -> 1 | ... P53: =IF(AND(P$3>=$C53,P$3<=$D53),1,"") -> 1
B54: D21 Handover package | C54: 12 | D54: 12 | E54: =IF(AND(E$3>=$C54,E$3<=$D54),1,"") | F54: =IF(AND(F$3>=$C54,F$3<=$D54),1,"") | G54: =IF(AND(G$3>=$C54,G$3<=$D54),1,"") | H54: =IF(AND(H$3>=$C54,H$3<=$D54),1,"") | I54: =IF(AND(I$3>=$C54,I$3<=$D54),1,"") | J54: =IF(AND(J$3>=$C54,J$3<=$D54),1,"") | K54: =IF(AND(K$3>=$C54,K$3<=$D54),1,"") | L54: =IF(AND(L$3>=$C54,L$3<=$D54),1,"") | ... P54: =IF(AND(P$3>=$C54,P$3<=$D54),1,"") -> 1
A55: Reporting | B55: R1 Quarterly report 1 | C55: 3 | D55: 3 | E55: =IF(AND(E$3>=$C55,E$3<=$D55),1,"") | F55: =IF(AND(F$3>=$C55,F$3<=$D55),1,"") | G55: =IF(AND(G$3>=$C55,G$3<=$D55),1,"") -> 1 | H55: =IF(AND(H$3>=$C55,H$3<=$D55),1,"") | I55: =IF(AND(I$3>=$C55,I$3<=$D55),1,"") | J55: =IF(AND(J$3>=$C55,J$3<=$D55),1,"") | K55: =IF(AND(K$3>=$C55,K$3<=$D55),1,"") | L55: =IF(AND(L$3>=$C55,L$3<=$D55),1,"") | ... P55: =IF(AND(P$3>=$C55,P$3<=$D55),1,"")
B56: R2 Quarterly report 2 and mid-year review | C56: 6 | D56: 6 | E56: =IF(AND(E$3>=$C56,E$3<=$D56),1,"") | F56: =IF(AND(F$3>=$C56,F$3<=$D56),1,"") | G56: =IF(AND(G$3>=$C56,G$3<=$D56),1,"") | H56: =IF(AND(H$3>=$C56,H$3<=$D56),1,"") | I56: =IF(AND(I$3>=$C56,I$3<=$D56),1,"") | J56: =IF(AND(J$3>=$C56,J$3<=$D56),1,"") -> 1 | K56: =IF(AND(K$3>=$C56,K$3<=$D56),1,"") | L56: =IF(AND(L$3>=$C56,L$3<=$D56),1,"") | ... P56: =IF(AND(P$3>=$C56,P$3<=$D56),1,"")
B57: D17 Actual cost report | C57: 9 | D57: 9 | E57: =IF(AND(E$3>=$C57,E$3<=$D57),1,"") | F57: =IF(AND(F$3>=$C57,F$3<=$D57),1,"") | G57: =IF(AND(G$3>=$C57,G$3<=$D57),1,"") | H57: =IF(AND(H$3>=$C57,H$3<=$D57),1,"") | I57: =IF(AND(I$3>=$C57,I$3<=$D57),1,"") | J57: =IF(AND(J$3>=$C57,J$3<=$D57),1,"") | K57: =IF(AND(K$3>=$C57,K$3<=$D57),1,"") | L57: =IF(AND(L$3>=$C57,L$3<=$D57),1,"") | ... P57: =IF(AND(P$3>=$C57,P$3<=$D57),1,"")
B58: R3 Quarterly report 3 | C58: 9 | D58: 9 | E58: =IF(AND(E$3>=$C58,E$3<=$D58),1,"") | F58: =IF(AND(F$3>=$C58,F$3<=$D58),1,"") | G58: =IF(AND(G$3>=$C58,G$3<=$D58),1,"") | H58: =IF(AND(H$3>=$C58,H$3<=$D58),1,"") | I58: =IF(AND(I$3>=$C58,I$3<=$D58),1,"") | J58: =IF(AND(J$3>=$C58,J$3<=$D58),1,"") | K58: =IF(AND(K$3>=$C58,K$3<=$D58),1,"") | L58: =IF(AND(L$3>=$C58,L$3<=$D58),1,"") | ... P58: =IF(AND(P$3>=$C58,P$3<=$D58),1,"")
B59: D22 Final report and dataset | C59: 12 | D59: 12 | E59: =IF(AND(E$3>=$C59,E$3<=$D59),1,"") | F59: =IF(AND(F$3>=$C59,F$3<=$D59),1,"") | G59: =IF(AND(G$3>=$C59,G$3<=$D59),1,"") | H59: =IF(AND(H$3>=$C59,H$3<=$D59),1,"") | I59: =IF(AND(I$3>=$C59,I$3<=$D59),1,"") | J59: =IF(AND(J$3>=$C59,J$3<=$D59),1,"") | K59: =IF(AND(K$3>=$C59,K$3<=$D59),1,"") | L59: =IF(AND(L$3>=$C59,L$3<=$D59),1,"") | ... P59: =IF(AND(P$3>=$C59,P$3<=$D59),1,"") -> 1
B60: R4 Quarterly report 4 | C60: 12 | D60: 12 | E60: =IF(AND(E$3>=$C60,E$3<=$D60),1,"") | F60: =IF(AND(F$3>=$C60,F$3<=$D60),1,"") | G60: =IF(AND(G$3>=$C60,G$3<=$D60),1,"") | H60: =IF(AND(H$3>=$C60,H$3<=$D60),1,"") | I60: =IF(AND(I$3>=$C60,I$3<=$D60),1,"") | J60: =IF(AND(J$3>=$C60,J$3<=$D60),1,"") | K60: =IF(AND(K$3>=$C60,K$3<=$D60),1,"") | L60: =IF(AND(L$3>=$C60,L$3<=$D60),1,"") | ... P60: =IF(AND(P$3>=$C60,P$3<=$D60),1,"") -> 1
A61: Year 2 | B61: D16 Year 2 proposal presented to the LGU | C61: 8 | D61: 8 | E61: =IF(AND(E$3>=$C61,E$3<=$D61),1,"") | F61: =IF(AND(F$3>=$C61,F$3<=$D61),1,"") | G61: =IF(AND(G$3>=$C61,G$3<=$D61),1,"") | H61: =IF(AND(H$3>=$C61,H$3<=$D61),1,"") | I61: =IF(AND(I$3>=$C61,I$3<=$D61),1,"") | J61: =IF(AND(J$3>=$C61,J$3<=$D61),1,"") | K61: =IF(AND(K$3>=$C61,K$3<=$D61),1,"") | L61: =IF(AND(L$3>=$C61,L$3<=$D61),1,"") -> 1 | ... P61: =IF(AND(P$3>=$C61,P$3<=$D61),1,"")
B62: D20 Year 2 commitment from New Washington | C62: 10 | D62: 11 | E62: =IF(AND(E$3>=$C62,E$3<=$D62),1,"") | F62: =IF(AND(F$3>=$C62,F$3<=$D62),1,"") | G62: =IF(AND(G$3>=$C62,G$3<=$D62),1,"") | H62: =IF(AND(H$3>=$C62,H$3<=$D62),1,"") | I62: =IF(AND(I$3>=$C62,I$3<=$D62),1,"") | J62: =IF(AND(J$3>=$C62,J$3<=$D62),1,"") | K62: =IF(AND(K$3>=$C62,K$3<=$D62),1,"") | L62: =IF(AND(L$3>=$C62,L$3<=$D62),1,"") | ... P62: =IF(AND(P$3>=$C62,P$3<=$D62),1,"")
B63: Gates (see Gates sheet) | F63: ▲ G1 | J63: ▲ G2 | P63: ▲ G3

Sheet Training Plan
A1: Training Plan: Fishers, MDRRMO and LGU
A2: Every session with its audience, length, topics, trainer, timing and how we check that people learned.
A4: ID | B4: Session | C4: Audience and size | D4: Length | E4: Topics | F4: Trainer | G4: When | H4: How we check learning
A5: T2 | B5: SOS response SOP workshop | C5: MDRRMO head and duty officers, Coast Guard and BFAR focal persons (6-10) | D5: Half day | E5: Who receives and acknowledges an SOS; target times (acknowledge within 10 min); escalation to Coast Guard and BFAR; contact tree; what to tell families; record keeping. | F5: Lenard + faculty leader | G5: ="M5 ("&TEXT(EDATE(Overview!$C$8,5-1),"mmm")&")" -> M5 (May) | H5: SOP signed by the MDRRMO head
A6: T3 | B6: MDRRMO operator training | C6: All operators on the duty rota (at least 4) | D6: 1 day (6 h) | E6: Dashboard log-in and roles; reading SOS alerts, boat position and drift; acknowledging; following the SOP; device health; what to do when the system is down; practice with live test SOS. | F6: Arnold, Lenard | G6: ="M6 ("&TEXT(EDATE(Overview!$C$8,6-1),"mmm")&")" -> M6 (Jun) | H6: Each operator acknowledges a test SOS within 2 min; post-test 80%+
A7: T4 | B7: Champion fisher training | C7: 5 respected fishers chosen with the fisherfolk association | D7: Half day + 1 week soft launch | E7: Everything in T5, plus how to help other fishers, how to report problems, basic troubleshooting. | F7: Doreen, Jade, Daniel | G7: ="M6 ("&TEXT(EDATE(Overview!$C$8,6-1),"mmm")&")" -> M6 (Jun) | H7: Competency checklist passed; can demonstrate to a peer
A8: T5 | B8: Fisher training batches (3) | C8: 20 boats, 1-2 fishers per boat (about 12-15 people per batch); family members welcome | D8: Half day each: 2 h classroom + 1 h practice at the shore | E8: What AqOne does and does not do; pairing phone and pod; sending SOS (app and pod button); what happens after an SOS; charging and battery level; strapping the pod; care and basic checks; privacy and consent; safety at sea reminders. | F8: Doreen, KC, Jade + champions | G8: ="M6 ("&TEXT(EDATE(Overview!$C$8,6-1),"mmm")&")" -> M6 (Jun) | H8: Every fisher sends an SOS and charges a pod unaided before receiving a pod; pre/post test
A9: T6 | B9: Joint response exercise | C9: MDRRMO, Coast Guard, BFAR, 5 champion fishers | D9: 1 day | E9: Tabletop walk-through of the SOP, then a field drill: a champion boat sends SOS, MDRRMO acknowledges, Coast Guard responds; debrief. | F9: Lenard, Arnold + MDRRMO | G9: ="M8 ("&TEXT(EDATE(Overview!$C$8,8-1),"mmm")&")" -> M8 (Aug) | H9: SOP followed end to end; lessons logged; SOP updated
A10: T7 | B10: Refresher training | C10: All active fishers and MDRRMO operators; replacement fishers | D10: 2 h per group | E10: Common mistakes found in the first 2 months; new app features; survey feedback; repeat practice SOS. | F10: Doreen, Jade, Arnold | G10: ="M9 ("&TEXT(EDATE(Overview!$C$8,9-1),"mmm")&")" -> M9 (Sep) | H10: Attendance; practice SOS by each participant
A11: T8 | B11: LGU technician maintenance training | C11: At least 2 LGU technicians | D11: 2 days | E11: Health dashboard; inspection checklist; swapping pod batteries; resealing enclosures; replacing antennas and arrestors; safety at height and at sea. | F11: Daniel | G11: ="M12 ("&TEXT(EDATE(Overview!$C$8,12-1),"mmm")&")" -> M12 (Dec) | H11: Each technician completes the tasks unaided
A12: T9 | B12: Training evaluation | C12: All trainings above | D12: - | E12: Attendance, pre/post tests, competency pass rates, participant feedback, improvements for Year 2. | F12: Doreen | G12: ="M12 ("&TEXT(EDATE(Overview!$C$8,12-1),"mmm")&")" -> M12 (Dec) | H12: Training evaluation report
A14: Training rules: materials in Aklanon first; sessions near the fish landing at times that avoid fishing hours; no fisher receives a pod before passing the competency check; attendance and consent recorded for every session.

Sheet Validation Plan
A1: Validation Plan
A2: What we measure to prove AqOne works, how, with how many, and what counts as a pass. The validation period is months 7-12; earlier items prove readiness.
A4: ID | B4: Test | C4: What we measure | D4: Method | E4: Sample | F4: Pass target | G4: When | H4: Owner
A5: V1 | B5: Validation protocol | C5: Defines every test below, data handling and consent | D5: Written protocol reviewed by the faculty leader | E5: - | F5: Approved before any field test | G5: ="M3 ("&TEXT(EDATE(Overview!$C$8,3-1),"mmm")&")" -> M3 (Mar) | H5: Lenard
A6: D5 | B6: Bench SOS test | C6: End-to-end delivery pod → gateway → dashboard; pod battery life | D6: Scripted test in the lab | E6: 100 messages; 3 pods for battery | F6: 100/100 delivered; battery 48 h+ | G6: ="M3 ("&TEXT(EDATE(Overview!$C$8,3-1),"mmm")&")" -> M3 (Mar) | H6: Daniel
A7: D9 | B7: Coverage survey | C7: LoRa signal strength and delivery by location | D7: Boat runs with a test pod; GPS-tagged readings | E7: 50+ points | F7: Coverage map; buoy positions confirmed | G7: ="M4 ("&TEXT(EDATE(Overview!$C$8,4-1),"mmm")&")" -> M4 (Apr) | H7: Daniel, Lenard
A8: V2 | B8: Soft launch | C8: Real-world use on 5 boats before full rollout | D8: 5 champion boats for 1 week | E8: 5 boats, 10+ messages each | F8: All messages delivered or issues logged and fixed | G8: ="M6 ("&TEXT(EDATE(Overview!$C$8,6-1),"mmm")&")" -> M6 (Jun) | H8: Lenard, Daniel
A9: V3 | B9: Usability test round 1 | C9: Can fishers use it without help? | D9: Observed tasks: pair, send SOS, check battery | E9: 10+ fishers | F9: 90%+ complete each task; SOS within 60 s | G9: ="M6 ("&TEXT(EDATE(Overview!$C$8,6-1),"mmm")&")" -> M6 (Jun) | H9: Jade
A10: D13 | B10: SOS acceptance test | C10: Delivery, speed, acknowledgement, failure handling | D10: Scheduled drills at 3+ locations; power and carrier cut tests | E10: 30+ drills | F10: 95%+ within 2 min; acknowledged within 10 min; failure tests passed | G10: ="M6 ("&TEXT(EDATE(Overview!$C$8,6-1),"mmm")&")" -> M6 (Jun) | H10: Lenard, Daniel
A11: D14 | B11: Six-month operation | C11: Uptime, outages, drills, inspections, active pods | D11: Monthly Ops sheet | E11: 6 months | F11: All 6 months PASS | G11: ="M12 ("&TEXT(EDATE(Overview!$C$8,12-1),"mmm")&")" -> M12 (Dec) | H11: Daniel, Lenard
A12: V4 | B12: Unannounced drills | C12: Real response when MDRRMO does not know it is a drill | D12: Faculty leader triggers a drill at a random time | E12: 1+ per month, M8-M12 | F12: Acknowledged within 10 min in 90%+ | G12: ="M12 ("&TEXT(EDATE(Overview!$C$8,12-1),"mmm")&")" -> M12 (Dec) | H12: Lenard + faculty leader
A13: V5 | B13: Night and rough-weather drills | C13: Performance in harder conditions | D13: Drills at night and in moderate seas, only when safe | E13: 3 night + 2 rough | F13: Same targets as D13 | G13: ="M8 ("&TEXT(EDATE(Overview!$C$8,8-1),"mmm")&")" -> M8 (Aug) | H13: Daniel, Lenard
A14: D15/D18 | B14: Fisher feedback surveys | C14: Satisfaction, trust, problems, suggestions | D14: Short survey in Aklanon | E14: 15+ boats each round | F14: Top issues logged and acted on | G14: ="M10 ("&TEXT(EDATE(Overview!$C$8,10-1),"mmm")&")" -> M10 (Oct) | H14: Doreen, KC
A15: V6 | B15: Mid-pilot review | C15: Are we on track against the protocol? | D15: Review meeting with ASU and MDRRMO | E15: M7-M8 data | F15: Decisions recorded | G15: ="M9 ("&TEXT(EDATE(Overview!$C$8,9-1),"mmm")&")" -> M9 (Sep) | H15: Lenard
A16: V7 | B16: Usability test round 2 | C16: Improvement since round 1 | D16: Repeat round 1 tasks | E16: 15+ fishers | F16: Equal or better than round 1 | G16: ="M10 ("&TEXT(EDATE(Overview!$C$8,10-1),"mmm")&")" -> M10 (Oct) | H16: Jade
A17: D19 | B17: Experimental AI evaluation | C17: Squall, drift and catch features on pilot data | D17: Compare predictions with observed events | E17: All pilot data | F17: Reported separately; no SOS claims depend on it | G17: ="M11 ("&TEXT(EDATE(Overview!$C$8,11-1),"mmm")&")" -> M11 (Nov) | H17: Lenard
A18: V8 | B18: Final validation report | C18: All results vs targets | D18: Compile raw data and results | E18: Whole pilot | F18: Complete report with limitations | G18: ="M12 ("&TEXT(EDATE(Overview!$C$8,12-1),"mmm")&")" -> M12 (Dec) | H18: Lenard + faculty leader
A20: Yellow test names fall inside the validation period (months 7-12). Every result goes into the final validation report (V8), including failures.

Sheet Promotion Plan
A1: Promotion Plan
A2: How we build awareness and trust in New Washington and prepare Year 2 customers.
A4: ID | B4: Activity | C4: Channel | D4: Audience | E4: When | F4: Owner | G4: Target (KPI)
A5: P1 | B5: Communication kit | C5: Internal | D5: Team, partners | E5: M1-M2 | F5: Doreen | G5: Key messages in 3 languages; consent form for photos
A6: P2 | B6: AqOne Facebook page | C6: Facebook (main channel) | D6: Fishers' families, community, LGUs | E6: M2-M12 | F6: Doreen, KC | G6: 2+ posts per week; monthly reach report
A7: P3 | B7: Barangay assemblies | C7: Face to face with LGU | D7: Fishers in coastal barangays | E7: M3-M4 | F7: Doreen, KC + LGU | G7: 4+ assemblies; 20 boats signed up + waitlist
A8: P4 | B8: IEC materials | C8: Tarpaulins, flyers (Aklanon) | D8: Fishers, port users, barangay halls | E8: M5 | F8: Doreen, KC | G8: Tarps placed at 4+ sites; flyers at every assembly
A9: P5 | B9: Community launch and demo day | C9: Public event | D9: Community, LGU, MDRRMO, Coast Guard, BFAR, ASU | E9: M7 | F9: Doreen, KC + LGU | G9: 60+ attendees; live SOS demo
A10: P6 | B10: Local media | C10: Press release, local radio | D10: Aklan public | E10: M7-M8 | F10: Doreen + ASU public affairs | G10: 1+ feature
A11: P7 | B11: Fisher stories | C11: Facebook, reports | D11: Community, investors, DOST | E11: M7-M11 | F11: Doreen, KC | G11: 3+ stories with consent
A12: P8 | B12: Stakeholder briefings (4) | C12: Meetings | D12: LGU, MDRRMO, BFAR, Coast Guard | E12: M3, M6, M9, M12 | F12: Doreen, Lenard | G12: Attendance and commitments recorded
A13: P9 | B13: Neighbouring LGU outreach | C13: Presentations | D13: 3+ Aklan coastal LGUs | E13: M10-M11 | F13: Doreen, KC + Lenard | G13: 1+ LOI (Year 2 pipeline)
A14: P10 | B14: Pilot results forum | C14: Public event | D14: Stakeholders, community | E14: M12 | F14: Doreen, KC + all | G14: Results presented; Year 2 partners invited
A15: D23 | B15: Conference abstract | C15: National research forum | D15: Researchers, DOST | E15: M12 | F15: Lenard + faculty leader | G15: Abstract submitted
A17: Promotion rules: never show a fisher's face, name or boat without signed consent; never promise coverage we have not measured; sponsor logos (Year 2) never appear on SOS or alert screens.

Sheet Monthly Ops
A1: Validation Period Tracker (Months 7-12)
A2: Type the actual numbers each month in the yellow cells. A month passes when every target is met.
A4: TARGETS (change here if ASU or MDRRMO agree different ones)
A5: Network uptime (minimum) | D5: 0.95
A6: Longest outage (max. hours) | D6: 6
A7: SOS drills (min. per month) | D7: 5
A8: Unannounced drills (min., from M8) | D8: 1
A9: Inspection trips (min. per month) | D9: 1
A10: Pods used on trips (min., of 20) | D10: 15
A12: Month | B12: Month name | C12: Uptime | D12: Longest outage (h) | E12: SOS drills | F12: Unannounced drills | G12: Inspection trips | H12: Pods used on trips | I12: Result | J12: Incidents and notes
A13: M7 | B13: =TEXT(EDATE(Overview!$C$8,7-1),"mmm yyyy") -> Jul 2027 | I13: =IF(COUNT(C13:H13)<6,"Pending",IF(AND(C13>=$D$5,D13<=$D$6,E13>=$D$7,F13>=0,G13>=$D$9,H13>=$D$10),"PASS","FAIL")) -> Pending
A14: M8 | B14: =TEXT(EDATE(Overview!$C$8,8-1),"mmm yyyy") -> Aug 2027 | I14: =IF(COUNT(C14:H14)<6,"Pending",IF(AND(C14>=$D$5,D14<=$D$6,E14>=$D$7,F14>=$D$8,G14>=$D$9,H14>=$D$10),"PASS","FAIL")) -> Pending
A15: M9 | B15: =TEXT(EDATE(Overview!$C$8,9-1),"mmm yyyy") -> Sep 2027 | I15: =IF(COUNT(C15:H15)<6,"Pending",IF(AND(C15>=$D$5,D15<=$D$6,E15>=$D$7,F15>=$D$8,G15>=$D$9,H15>=$D$10),"PASS","FAIL")) -> Pending
A16: M10 | B16: =TEXT(EDATE(Overview!$C$8,10-1),"mmm yyyy") -> Oct 2027 | I16: =IF(COUNT(C16:H16)<6,"Pending",IF(AND(C16>=$D$5,D16<=$D$6,E16>=$D$7,F16>=$D$8,G16>=$D$9,H16>=$D$10),"PASS","FAIL")) -> Pending
A17: M11 | B17: =TEXT(EDATE(Overview!$C$8,11-1),"mmm yyyy") -> Nov 2027 | I17: =IF(COUNT(C17:H17)<6,"Pending",IF(AND(C17>=$D$5,D17<=$D$6,E17>=$D$7,F17>=$D$8,G17>=$D$9,H17>=$D$10),"PASS","FAIL")) -> Pending
A18: M12 | B18: =TEXT(EDATE(Overview!$C$8,12-1),"mmm yyyy") -> Dec 2027 | I18: =IF(COUNT(C18:H18)<6,"Pending",IF(AND(C18>=$D$5,D18<=$D$6,E18>=$D$7,F18>=$D$8,G18>=$D$9,H18>=$D$10),"PASS","FAIL")) -> Pending
A20: Months passed | C20: =COUNTIF(I13:I18,"PASS")&" of 6" -> 0 of 6 | J20: D14 is met when all 6 months pass. In M7, unannounced drills are not yet required.

Sheet Gates
A1: Gates and Investor Milestone 1
A2: Each gate lists the deliverables it needs. Status is read from the Deliverables sheet.
A4: G1 Go/no-go on LGU agreement
A5: Deadline | B5: =EOMONTH(Overview!$C$8,2-1) -> 46446
A6: Needs deliverable | B6: ID | C6: Due date | D6: Status | E6: Pass/fail test
A7: =INDEX(Deliverables!$C$5:$C$61,MATCH(B7,Deliverables!$A$5:$A$61,0)) -> LGU agreement and MDRRMO commitment | B7: D4 | C7: =INDEX(Deliverables!$F$5:$F$61,MATCH(B7,Deliverables!$A$5:$A$61,0)) -> 46446 | D7: =INDEX(Deliverables!$K$5:$K$61,MATCH(B7,Deliverables!$A$5:$A$61,0)) -> Not started | E7: =INDEX(Deliverables!$H$5:$H$61,MATCH(B7,Deliverables!$A$5:$A$61,0)) -> Signed MOA or LOI covering host buoys, boat access, 2 gateway sites and permits; MDRRMO agrees to monitor alerts and run drills.
A8: Gate result | D8: =IF(COUNTIF(D7:D7,"Done")=1,"MET","NOT YET") -> NOT YET | E8: If not met: switch to plan B (ASU-arranged boats, buoys and gateway sites) before installation.
A10: G2 Go-live
A11: Deadline | B11: =EOMONTH(Overview!$C$8,6-1) -> 46568
A12: Needs deliverable | B12: ID | C12: Due date | D12: Status | E12: Pass/fail test
A13: =INDEX(Deliverables!$C$5:$C$61,MATCH(B13,Deliverables!$A$5:$A$61,0)) -> SOS response procedure (SOP) signed with MDRRMO | B13: T2 | C13: =INDEX(Deliverables!$F$5:$F$61,MATCH(B13,Deliverables!$A$5:$A$61,0)) -> 46538 | D13: =INDEX(Deliverables!$K$5:$K$61,MATCH(B13,Deliverables!$A$5:$A$61,0)) -> Not started | E13: =INDEX(Deliverables!$H$5:$H$61,MATCH(B13,Deliverables!$A$5:$A$61,0)) -> Written SOP: who acknowledges an SOS, target times, escalation to Coast Guard and BFAR, contact tree; signed off by the MDRRMO head.
A14: =INDEX(Deliverables!$C$5:$C$61,MATCH(B14,Deliverables!$A$5:$A$61,0)) -> MDRRMO operator training | B14: T3 | C14: =INDEX(Deliverables!$F$5:$F$61,MATCH(B14,Deliverables!$A$5:$A$61,0)) -> 46568 | D14: =INDEX(Deliverables!$K$5:$K$61,MATCH(B14,Deliverables!$A$5:$A$61,0)) -> Not started | E14: =INDEX(Deliverables!$H$5:$H$61,MATCH(B14,Deliverables!$A$5:$A$61,0)) -> All operators on the duty rota (at least 4) trained; each acknowledges a test SOS on the dashboard within 2 minutes; post-test score 80% or higher.
A15: =INDEX(Deliverables!$C$5:$C$61,MATCH(B15,Deliverables!$A$5:$A$61,0)) -> Fisher training batches and competency check | B15: T5 | C15: =INDEX(Deliverables!$F$5:$F$61,MATCH(B15,Deliverables!$A$5:$A$61,0)) -> 46568 | D15: =INDEX(Deliverables!$K$5:$K$61,MATCH(B15,Deliverables!$A$5:$A$61,0)) -> Not started | E15: =INDEX(Deliverables!$H$5:$H$61,MATCH(B15,Deliverables!$A$5:$A$61,0)) -> 3 batches covering all 20 boats (1-2 fishers per boat). Every fisher sends an SOS and charges a pod without help before receiving a pod; pre/post test gain recorded.
A16: =INDEX(Deliverables!$C$5:$C$61,MATCH(B16,Deliverables!$A$5:$A$61,0)) -> 20 boats onboarded | B16: D12 | C16: =INDEX(Deliverables!$F$5:$F$61,MATCH(B16,Deliverables!$A$5:$A$61,0)) -> 46568 | D16: =INDEX(Deliverables!$K$5:$K$61,MATCH(B16,Deliverables!$A$5:$A$61,0)) -> Not started | E16: =INDEX(Deliverables!$H$5:$H$61,MATCH(B16,Deliverables!$A$5:$A$61,0)) -> 20 boats have pods; consent forms signed; pod serial numbers matched to boats in the dashboard.
A17: =INDEX(Deliverables!$C$5:$C$61,MATCH(B17,Deliverables!$A$5:$A$61,0)) -> SOS acceptance test passed (go-live) | B17: D13 | C17: =INDEX(Deliverables!$F$5:$F$61,MATCH(B17,Deliverables!$A$5:$A$61,0)) -> 46568 | D17: =INDEX(Deliverables!$K$5:$K$61,MATCH(B17,Deliverables!$A$5:$A$61,0)) -> Not started | E17: =INDEX(Deliverables!$H$5:$H$61,MATCH(B17,Deliverables!$A$5:$A$61,0)) -> At least 30 drills at 3+ locations; 95%+ reach the dashboard within 2 min; MDRRMO acknowledges within 10 min; gateway power-loss and carrier-loss tests passed.
A18: Gate result | D18: =IF(COUNTIF(D13:D17,"Done")=5,"MET","NOT YET") -> NOT YET | E18: If not met: do not go live; fix, re-test within 4 weeks.
A20: G3 Investor Milestone 1 (unlocks ₱3M)
A21: Deadline | B21: =EOMONTH(Overview!$C$8,12-1) -> 46752
A22: Needs deliverable | B22: ID | C22: Due date | D22: Status | E22: Pass/fail test
A23: =INDEX(Deliverables!$C$5:$C$61,MATCH(B23,Deliverables!$A$5:$A$61,0)) -> SOS acceptance test passed (go-live) | B23: D13 | C23: =INDEX(Deliverables!$F$5:$F$61,MATCH(B23,Deliverables!$A$5:$A$61,0)) -> 46568 | D23: =INDEX(Deliverables!$K$5:$K$61,MATCH(B23,Deliverables!$A$5:$A$61,0)) -> Not started | E23: =INDEX(Deliverables!$H$5:$H$61,MATCH(B23,Deliverables!$A$5:$A$61,0)) -> At least 30 drills at 3+ locations; 95%+ reach the dashboard within 2 min; MDRRMO acknowledges within 10 min; gateway power-loss and carrier-loss tests passed.
A24: =INDEX(Deliverables!$C$5:$C$61,MATCH(B24,Deliverables!$A$5:$A$61,0)) -> Six-month validation period (supported SOS operation) | B24: D14 | C24: =INDEX(Deliverables!$F$5:$F$61,MATCH(B24,Deliverables!$A$5:$A$61,0)) -> 46752 | D24: =INDEX(Deliverables!$K$5:$K$61,MATCH(B24,Deliverables!$A$5:$A$61,0)) -> Not started | E24: =INDEX(Deliverables!$H$5:$H$61,MATCH(B24,Deliverables!$A$5:$A$61,0)) -> Every month meets the Monthly Ops targets: uptime, longest outage, drills (including unannounced), inspections, active pods.
A25: =INDEX(Deliverables!$C$5:$C$61,MATCH(B25,Deliverables!$A$5:$A$61,0)) -> Actual cost report | B25: D17 | C25: =INDEX(Deliverables!$F$5:$F$61,MATCH(B25,Deliverables!$A$5:$A$61,0)) -> 46660 | D25: =INDEX(Deliverables!$K$5:$K$61,MATCH(B25,Deliverables!$A$5:$A$61,0)) -> Not started | E25: =INDEX(Deliverables!$H$5:$H$61,MATCH(B25,Deliverables!$A$5:$A$61,0)) -> Real cost of buoy node, pod and gateway vs budget, with variances explained.
A26: =INDEX(Deliverables!$C$5:$C$61,MATCH(B26,Deliverables!$A$5:$A$61,0)) -> Year 2 commitment from New Washington | B26: D20 | C26: =INDEX(Deliverables!$F$5:$F$61,MATCH(B26,Deliverables!$A$5:$A$61,0)) -> 46721 | D26: =INDEX(Deliverables!$K$5:$K$61,MATCH(B26,Deliverables!$A$5:$A$61,0)) -> Not started | E26: =INDEX(Deliverables!$H$5:$H$61,MATCH(B26,Deliverables!$A$5:$A$61,0)) -> Paid Year 2 agreement or LOI signed.
A27: Gate result | D27: =IF(COUNTIF(D23:D26,"Done")=4,"MET","NOT YET") -> NOT YET | E27: If not met: the investor may decline tranche 1. Proof: DOST/ASU reports, dashboard logs, signed Year 2 document.
A29: Investor Milestone 2 (end of Year 2, unlocks ₱5M): 3 paying municipalities, 150+ active pods, 1+ co-op purchase agreement, pilot LGU renews, deployment gross margin 35%+. P9 (neighbouring LGU outreach) starts that pipeline.

Sheet Budget Notes
A1: Budget Notes: Costs This Plan Adds
A2: The current budget has only ₱8,000 for outreach (B.6). These promotion and training costs are estimates and are NOT yet in Aquanons_Master_Budget.xlsx. Decide with ASU which to add.
A4: For | B4: Item | C4: Qty | D4: Unit cost | E4: Total | F4: Basis
A5: T4, T5 | B5: Fisher training snacks and meals | C5: 50 | D5: 150 | E5: =C5*D5 -> 7500 | F5: About 45 fishers in 3 batches + 5 champions (estimate)
A6: T7 | B6: Refresher training snacks | C6: 40 | D6: 150 | E6: =C6*D6 -> 6000 | F6: Fishers and operators (estimate)
A7: T2, T3, T6 | B7: MDRRMO workshops and joint exercise snacks | C7: 30 | D7: 150 | E7: =C7*D7 -> 4500 | F7: SOP workshop, operator training, joint exercise (estimate)
A8: T1, D10 | B8: Printed training handouts and picture guides | C8: 60 | D8: 50 | E8: =C8*D8 -> 3000 | F8: One per trained person plus spares (estimate)
A9: P3 | B9: Barangay assembly snacks | C9: 120 | D9: 60 | E9: =C9*D9 -> 7200 | F9: 4 assemblies × about 30 people (estimate)
A10: P4 | B10: Tarpaulins | C10: 6 | D10: 800 | E10: =C10*D10 -> 4800 | F10: Fish landing, port, barangay halls, MDRRMO (estimate)
A11: P4 | B11: Flyers in Aklanon | C11: 500 | D11: 6 | E11: =C11*D11 -> 3000 | F11: Estimate
A12: P5 | B12: Launch and demo day snacks | C12: 60 | D12: 150 | E12: =C12*D12 -> 9000 | F12: Venue from the LGU in kind (estimate)
A13: P5 | B13: Launch tarpaulin and program printing | C13: 1 | D13: 2000 | E13: =C13*D13 -> 2000 | F13: Estimate
A14: P10 | B14: Results forum snacks | C14: 40 | D14: 150 | E14: =C14*D14 -> 6000 | F14: Estimate
A15: P9 | B15: Travel to 3 neighbouring LGUs | C15: 3 | D15: 1500 | E15: =C15*D15 -> 4500 | F15: Public transport rate for a small team (estimate)
A16: P2 | B16: Facebook post boosting | C16: 10 | D16: 500 | E16: =C16*D16 -> 5000 | F16: ₱500/month M3-M12; CONFIRM DOST allows paid promotion (estimate)
B17: Total added by this plan | E17: =SUM(E5:E16) -> 62500
B18: Already in the budget (B.6 pilot community outreach) | E18: 8000
B19: Extra needed beyond the current budget | E19: =E17-E18 -> 54500
A21: Confirm with ASU: whether meals and snacks for trainings are allowed and at what rate, and whether paid social media promotion is an eligible expense. Adding the extra amount raises the grant request (plus 5% contingency if allowed).
