Workbook

Sheet Summary
A1: AqOne Investor Summary
A2: Hybrid deal: equity plus per-unit royalties, paid in two tranches after the DOST-funded pilot year. Draft for the startup competition; validate the yellow assumptions.
A4: THE ASK
A5: Total commitment | B5: ='Deal Terms'!$B$7+'Deal Terms'!$C$7 -> 8000000
A6: Tranche 1 (end of Y1, after milestone 1) | B6: ='Deal Terms'!$B$7 -> 3000000
A7: Tranche 2 (end of Y2, after milestone 2) | B7: ='Deal Terms'!$C$7 -> 5000000
A8: Investor ownership after both tranches | B8: ='Deal Terms'!B10 -> 0.12266667
A9: Royalty per boat pod sold | B9: ='Deal Terms'!$B$14 -> 750
A10: Royalty per paying municipality, per year | B10: ='Deal Terms'!$B$15 -> 12500
A11: Royalty cap (multiple of money paid in) | B11: ='Deal Terms'!$B$16 -> 1
A13: OUTCOMES BY SCENARIO
B14: Low | C14: Base | D14: High
A15: Paying municipalities (Y5) | B15: =Projections!G7 -> 24.898 | C15: =Projections!G45 -> 47.167 | D15: =Projections!G83 -> 75.775
A16: Active boat pods (Y5) | B16: =Projections!G9 -> 2296 | C16: =Projections!G47 -> 4275 | D16: =Projections!G85 -> 6902
A17: Revenue (Y5) | B17: =Projections!G15 -> 37738880 | C17: =Projections!G53 -> 71392670 | D17: =Projections!G91 -> 114751250
A18: EBITDA (Y5) | B18: =Projections!G24 -> 5914527.4 | C18: =Projections!G62 -> 22450973 | D18: =Projections!G100 -> 43872915
A19: Pod sales share of Y5 revenue | B19: =Projections!G12/Projections!G15 -> 0.65649802 | C19: =Projections!G50/Projections!G53 -> 0.65726916 | D19: =Projections!G88/Projections!G91 -> 0.65708304
A20: Deepest cash need with no investor money | B20: =MIN(Projections!C34:G34) -> -7879595.8 | C20: =MIN(Projections!C72:G72) -> -4783611.7 | D20: =MIN(Projections!C110:G110) -> -2881513.3
A21: Lowest cash point Y2-Y5 (before that year's tranche) | B21: =MIN(Projections!D35:G35) -> 120404.23 | C21: =MIN(Projections!D73:G73) -> 139472.5 | D21: =MIN(Projections!D111:G111) -> 145787.5
A22: Bridge financing needed (total) | B22: =Projections!G39 -> 0 | C22: =Projections!G77 -> 0 | D22: =Projections!G115 -> 0
A23: Investor ownership at exit (after later round and bridge) | B23: =Projections!G40 -> 0.098133333 | C23: =Projections!G78 -> 0.098133333 | D23: =Projections!G116 -> 0.098133333
A24: Royalties received by investor by Y5 | B24: ='Investor Returns'!B12 -> 2245975 | C24: ='Investor Returns'!B29 -> 4199962.5 | D24: ='Investor Returns'!B46 -> 6776812.5
A25: Equity value at exit (end of Y5) | B25: ='Investor Returns'!B13 -> 7406884.2 | C25: ='Investor Returns'!B30 -> 21018002 | D25: ='Investor Returns'!B47 -> 45043691
A26: Investor money multiple | B26: ='Investor Returns'!B14 -> 1.2066074 | C26: ='Investor Returns'!B31 -> 3.1522456 | D26: ='Investor Returns'!B48 -> 6.4775629
A27: Investor annualized return (IRR) | B27: ='Investor Returns'!B15 -> 0.059845203 | C27: ='Investor Returns'!B32 -> 0.41844772 | D27: ='Investor Returns'!B49 -> 0.75695384
A28: Money multiple with no exit (royalties only) | B28: ='Investor Returns'!B17 -> 0.28074688 | C28: ='Investor Returns'!B34 -> 0.52499531 | D28: ='Investor Returns'!B51 -> 0.84710156
A29: Annualized return with no exit | B29: ='Investor Returns'!B19 -> -0.36173008 | C29: ='Investor Returns'!B36 -> -0.20480588 | D29: ='Investor Returns'!B53 -> -0.057962974
A32: Y1 is funded by the DOST grant: investors pay nothing and receive nothing that year.
A33: Royalties are paid only from commercial revenue, never from DOST grant funds.
A34: Any shortfall is covered by bridge financing raised at the tranche 2 valuation, which dilutes the investor; slower hiring is the alternative.
A35: Pod unit margin at ₱19,900 price and ₱17,500 cost is ₱2,400 (12.1%); the ₱750 royalty leaves ₱1,650 before other costs.
A36: Unit costs come from the DOST Master Budget. Prices, deployment pace, cancellation rate and exit multiples are assumptions to validate.
A37: Illustrative terms for a competition pitch. Final terms are agreed privately with each investor (SEC rules on public offers).

Sheet Assumptions
A1: AqOne Investor Model - Assumptions
A2: Blue = editable input. Yellow = key assumption to validate with the pilot, LGUs and co-ops. Sources in column D.
A4: MARKET ANCHORS (reference, not used in formulas)
A5: Registered municipal fishing boats, Philippines (BoatR 2024) | B5: 442014 | D5: Oceana, Philippine Fisheries Assessment (2026), citing BFAR BoatR
A6: Registered municipal fisherfolk (FishR 2024, low estimate) | B6: 2372605 | D6: Oceana, Philippine Fisheries Assessment (2026); sources conflict up to 2.6M
A7: New Washington annual revenue, 2024 | B7: 203200000 | D7: Wikipedia, New Washington, Aklan (2024 financials)
A8: LDRRMF share of regular revenue (legal minimum) | B8: 0.05 | D8: RA 10121: at least 5% of estimated revenue from regular sources
A9: Average municipal fisher household income, per month (2018) | B9: 15707 | D9: Wikipedia, Municipal fisheries in the Philippines (PSA data)
A10: UNIT COSTS (from the DOST Master Budget, 28 Sep 2026)
A11: Buoy relay node, per unit | B11: 64150 | D11: Master Budget B.1.1-B.1.7
A12: Buoy relay nodes per municipality | B12: 3 | D12: Pilot assumption
A13: Shore gateway, per unit | B13: 37400 | D13: Master Budget B.1.9
A14: Shore gateways per municipality | B14: 2 | D14: Pilot assumption
A15: Installation, commissioning and training, per municipality | B15: 60000 | D15: Estimate: field labor, travel, LGU and fisher training
A16: Boat pod, per unit | B16: 17500 | D16: Master Budget B.1.8, including the physical SOS button
A17: Recurring cost per active municipality, per year | B17: 90000 | D17: Gateway SIMs ₱24k, SMS ₱15k, share of hosting, maintenance visits (Master Budget B.3-B.4)
A18: Service cost per active pod, per year | B18: 300 | D18: Estimate: support, app and data costs per boat
A19: Pod replacement and repair reserve, per active pod per year (% of pod cost) | B19: 0.05 | D19: Estimate: covers damaged or lost pods and parts; ₱300 alone would cover only ~1.75% replacement
A20: Infrastructure cost decline per year | B20: 0.07 | D20: Estimate: volume buying
A21: Pod cost decline per year | B21: 0.12 | D21: Estimate: custom boards replace dev modules; target ~₱10k by Y5
A22: PRICING
A23: LGU annual subscription (equipment lease + platform + maintenance) | B23: 350000 | D23: Assumption: ≈3.5% of a ~₱10M LDRRMF; validate with New Washington
A24: Boat pod price (co-op purchase, installment via co-op/MFI) | B24: 19900 | D24: Assumption; ≈1.3 months of fisher income, so a co-pay is likely needed
A25: Pod service fee, per active pod per year | B25: 1200 | D25: Assumption: ₱100/month per boat
A26: Local sponsorship revenue per active municipality, per year | B26: 60000 | D26: Estimate: 2 local sponsors (fuel suppliers, fish traders, co-ops, rural banks) × ₱2,500/month on the weather and advisory screens; never on SOS or alert screens
A27: Sponsorship sales and servicing cost | B27: 0.15 | D27: Estimate: share of sponsorship revenue
A28: GROWTH AND OPERATIONS
A29: Pods sold per active municipality per year (from Y2) | B29: 50 | D29: Assumption: co-op driven
A30: Municipality cancellation rate per year | B30: 0.1 | D30: Assumption
A31: Later funding round dilution before exit | B31: 0.2 | D31: Assumption: one seed round between tranche 2 and exit
A32: Y1 company costs funded outside the grant and investors | B32: 800000 | D32: Company setup, legal work and the ASU IP license; not in the DOST budget. Source: competition prizes or founders. CONFIRM no overlap with grant lines
A34: YEARLY INPUTS | C34: Y1 (DOST pilot) | D34: Y2 | E34: Y3 | F34: Y4 | G34: Y5
A35: New paying municipalities per year (base case) | C35: 0 | D35: 3 | E35: 8 | F35: 15 | G35: 25
A36: Company fixed costs per year (team, sales, legal, office, base hosting) | C36: 800000 | D36: 3500000 | E36: 6000000 | F36: 10000000 | G36: 16000000
A37: Y1 is the DOST-funded pilot: no commercial sales, no investor money, no returns. Pilot hardware is in the DOST budget; the Y1 fixed cost here is company setup only.
A39: SCENARIOS
A40: Scenario | B40: Deployment pace | C40: Exit multiple | D40: Exit value = Y5 revenue × multiple. Pace scales new municipalities; fixed costs from Y2 scale partly with pace (Y1 setup cost is fixed).
A41: Low | B41: 0.5 | C41: 2
A42: Base | B42: 1 | C42: 3
A43: High | B43: 1.6 | C43: 4

Sheet Deal Terms
A1: AqOne Investor Terms - Hybrid, Milestone-Tranched
A2: Investors commit now at today's valuation and pay only after each milestone is met. No money and no returns during the DOST-funded pilot year.
A4: TRANCHES
B5: Tranche 1 | C5: Tranche 2 | D5: Notes
A6: Paid at | B6: End of Y1 | C6: End of Y2 | D6: Each tranche is paid only when its milestone below is verified.
A7: Amount | B7: 3000000 | C7: 5000000
A8: Post-money valuation for the tranche | B8: 50000000 | C8: 75000000 | D8: Tranche 2 is priced higher because milestone 1 has removed risk.
A9: Equity issued for the tranche | B9: =B7/B8 -> 0.06 | C9: =C7/C8 -> 0.066666667 | D9: Hybrid terms: less equity than an equity-only deal because royalties return the investor's money first.
A10: Investor ownership after both tranches | B10: =B9*(1-C9)+C9 -> 0.12266667 | D10: Tranche 1 stake is diluted slightly when tranche 2 shares are issued.
A11: Ownership at exit before any bridge (after later round) | B11: =B10*(1-Assumptions!$B$31) -> 0.098133333
A13: ROYALTY (paid from commercial revenue only, never from DOST funds)
A14: Royalty per boat pod sold | B14: 750
A15: Royalty per paying municipality, per year | B15: 12500
A16: Royalty cap, as a multiple of money paid in | B16: 1 | D16: Royalties stop once the investor has received this multiple of what they have paid in. The equity stays.
A17: Share of royalty rates paid in Y2 (after tranche 1 only) | B17: 0.5 | D17: Half rates in Y2, full rates from Y3 (after tranche 2). No royalties in Y1.
A18: Share of royalty rates paid from Y3 | B18: 1
A20: MILESTONES
A21: Before any tranche | B21: DOST grant approved; company registered with SEC; IP license or assignment signed with ASU; term sheet signed.
A22: Milestone 1 (unlocks tranche 1, end of Y1) | B22: Pilot live in New Washington: 3 buoy relay nodes, 2 shore gateways, 18+ boat pods at sea. Network uptime ≥95% over the last 3 months. ≥95% of SOS drill messages delivered. Agreed number of active fishers. Paid Y2 service agreement or LOI from New Washington. Measured real unit costs.
A23: Milestone 2 (unlocks tranche 2, end of Y2) | B23: 3 paying municipalities. 150+ active boat pods. At least 1 co-op purchase agreement. Pilot LGU renews. Deployment gross margin ≥35%.
A24: If a milestone is missed | B24: The investor may decline the next tranche and keeps what was already issued. Fallback if DOST is delayed or rejected: the investor may fund the pilot directly at an agreed valuation.

Sheet Projections
A1: AqOne 5-Year Projections - Low, Base and High
A2: All figures in PHP. Y1 is the DOST pilot. Formulas only; change inputs on the Assumptions and Deal Terms sheets.
A4: LOW CASE
C5: Y1 (DOST pilot) | D5: Y2 | E5: Y3 | F5: Y4 | G5: Y5
A6: New paying municipalities | B6: =Assumptions!$B$41 -> 0.5 | C6: =ROUND(Assumptions!C$35*Assumptions!$B$41,0) -> 0 | D6: =ROUND(Assumptions!D$35*Assumptions!$B$41,0) -> 2 | E6: =ROUND(Assumptions!E$35*Assumptions!$B$41,0) -> 4 | F6: =ROUND(Assumptions!F$35*Assumptions!$B$41,0) -> 8 | G6: =ROUND(Assumptions!G$35*Assumptions!$B$41,0) -> 13
A7: Active paying municipalities | C7: =C6 -> 0 | D7: =C7*(1-Assumptions!$B$30)+D6 -> 2 | E7: =D7*(1-Assumptions!$B$30)+E6 -> 5.8 | F7: =E7*(1-Assumptions!$B$30)+F6 -> 13.22 | G7: =F7*(1-Assumptions!$B$30)+G6 -> 24.898
A8: Boat pods sold | C8: =0 -> 0 | D8: =ROUND(D7*Assumptions!$B$29,0) -> 100 | E8: =ROUND(E7*Assumptions!$B$29,0) -> 290 | F8: =ROUND(F7*Assumptions!$B$29,0) -> 661 | G8: =ROUND(G7*Assumptions!$B$29,0) -> 1245
A9: Active boat pods | C9: =C8 -> 0 | D9: =C9+D8 -> 100 | E9: =D9+E8 -> 390 | F9: =E9+F8 -> 1051 | G9: =F9+G8 -> 2296
A10: REVENUE
A11: LGU subscriptions | C11: =C7*Assumptions!$B$23 -> 0 | D11: =D7*Assumptions!$B$23 -> 700000 | E11: =E7*Assumptions!$B$23 -> 2030000 | F11: =F7*Assumptions!$B$23 -> 4627000 | G11: =G7*Assumptions!$B$23 -> 8714300
A12: Boat pod sales | C12: =C8*Assumptions!$B$24 -> 0 | D12: =D8*Assumptions!$B$24 -> 1990000 | E12: =E8*Assumptions!$B$24 -> 5771000 | F12: =F8*Assumptions!$B$24 -> 13153900 | G12: =G8*Assumptions!$B$24 -> 24775500
A13: Pod service fees | C13: =C9*Assumptions!$B$25 -> 0 | D13: =D9*Assumptions!$B$25 -> 120000 | E13: =E9*Assumptions!$B$25 -> 468000 | F13: =F9*Assumptions!$B$25 -> 1261200 | G13: =G9*Assumptions!$B$25 -> 2755200
A14: Local sponsorships | C14: =C7*Assumptions!$B$26 -> 0 | D14: =D7*Assumptions!$B$26 -> 120000 | E14: =E7*Assumptions!$B$26 -> 348000 | F14: =F7*Assumptions!$B$26 -> 793200 | G14: =G7*Assumptions!$B$26 -> 1493880
A15: Total revenue | C15: =SUM(C11:C14) -> 0 | D15: =SUM(D11:D14) -> 2930000 | E15: =SUM(E11:E14) -> 8617000 | F15: =SUM(F11:F14) -> 19835300 | G15: =SUM(G11:G14) -> 37738880
A16: COSTS
A17: Recurring cost of active municipalities | C17: =C7*Assumptions!$B$17 -> 0 | D17: =D7*Assumptions!$B$17 -> 180000 | E17: =E7*Assumptions!$B$17 -> 522000 | F17: =F7*Assumptions!$B$17 -> 1189800 | G17: =G7*Assumptions!$B$17 -> 2240820
A18: Cost of pods sold | C18: =C8*Assumptions!$B$16*(1-Assumptions!$B$21)^0 -> 0 | D18: =D8*Assumptions!$B$16*(1-Assumptions!$B$21)^1 -> 1540000 | E18: =E8*Assumptions!$B$16*(1-Assumptions!$B$21)^2 -> 3930080 | F18: =F8*Assumptions!$B$16*(1-Assumptions!$B$21)^3 -> 7882927.4 | G18: =G8*Assumptions!$B$16*(1-Assumptions!$B$21)^4 -> 13065863
A19: Pod service cost | C19: =C9*(Assumptions!$B$18+Assumptions!$B$19*Assumptions!$B$16*(1-Assumptions!$B$21)^0) -> 0 | D19: =D9*(Assumptions!$B$18+Assumptions!$B$19*Assumptions!$B$16*(1-Assumptions!$B$21)^1) -> 107000 | E19: =E9*(Assumptions!$B$18+Assumptions!$B$19*Assumptions!$B$16*(1-Assumptions!$B$21)^2) -> 381264 | F19: =F9*(Assumptions!$B$18+Assumptions!$B$19*Assumptions!$B$16*(1-Assumptions!$B$21)^3) -> 941998.69 | G19: =G9*(Assumptions!$B$18+Assumptions!$B$19*Assumptions!$B$16*(1-Assumptions!$B$21)^4) -> 1893588
A20: Sponsorship sales cost | C20: =C14*Assumptions!$B$27 -> 0 | D20: =D14*Assumptions!$B$27 -> 18000 | E20: =E14*Assumptions!$B$27 -> 52200 | F20: =F14*Assumptions!$B$27 -> 118980 | G20: =G14*Assumptions!$B$27 -> 224082
A21: Gross profit | C21: =C15-SUM(C17:C20) -> 0 | D21: =D15-SUM(D17:D20) -> 1085000 | E21: =E15-SUM(E17:E20) -> 3731456 | F21: =F15-SUM(F17:F20) -> 9701594 | G21: =G15-SUM(G17:G20) -> 20314527
A22: Gross margin | C22: =IF(C15=0,0,C21/C15) -> 0 | D22: =IF(D15=0,0,D21/D15) -> 0.37030717 | E22: =IF(E15=0,0,E21/E15) -> 0.43303423 | F22: =IF(F15=0,0,F21/F15) -> 0.4891075 | G22: =IF(G15=0,0,G21/G15) -> 0.53829174
A23: Company fixed costs | C23: =Assumptions!C$36 -> 800000 | D23: =Assumptions!D$36*(0.8+0.2*Assumptions!$B$41) -> 3150000 | E23: =Assumptions!E$36*(0.8+0.2*Assumptions!$B$41) -> 5400000 | F23: =Assumptions!F$36*(0.8+0.2*Assumptions!$B$41) -> 9000000 | G23: =Assumptions!G$36*(0.8+0.2*Assumptions!$B$41) -> 14400000
A24: EBITDA | C24: =C21-C23 -> -800000 | D24: =D21-D23 -> -2065000 | E24: =E21-E23 -> -1668544 | F24: =F21-F23 -> 701593.95 | G24: =G21-G23 -> 5914527.4
A25: Equipment for new municipalities (company-owned, leased) | C25: =C6*(Assumptions!$B$11*Assumptions!$B$12+Assumptions!$B$13*Assumptions!$B$14+Assumptions!$B$15)*(1-Assumptions!$B$20)^0 -> 0 | D25: =D6*(Assumptions!$B$11*Assumptions!$B$12+Assumptions!$B$13*Assumptions!$B$14+Assumptions!$B$15)*(1-Assumptions!$B$20)^1 -> 608685 | E25: =E6*(Assumptions!$B$11*Assumptions!$B$12+Assumptions!$B$13*Assumptions!$B$14+Assumptions!$B$15)*(1-Assumptions!$B$20)^2 -> 1132154.1 | F25: =F6*(Assumptions!$B$11*Assumptions!$B$12+Assumptions!$B$13*Assumptions!$B$14+Assumptions!$B$15)*(1-Assumptions!$B$20)^3 -> 2105806.6 | G25: =G6*(Assumptions!$B$11*Assumptions!$B$12+Assumptions!$B$13*Assumptions!$B$14+Assumptions!$B$15)*(1-Assumptions!$B$20)^4 -> 3182400.3
A26: INVESTOR
A27: Investor money paid in, cumulative (start of year) | C27: =0 -> 0 | D27: ='Deal Terms'!$B$7 -> 3000000 | E27: ='Deal Terms'!$B$7+'Deal Terms'!$C$7 -> 8000000 | F27: ='Deal Terms'!$B$7+'Deal Terms'!$C$7 -> 8000000 | G27: ='Deal Terms'!$B$7+'Deal Terms'!$C$7 -> 8000000
A28: Royalty earned at tranche-based rates | C28: =(C8*'Deal Terms'!$B$14+C7*'Deal Terms'!$B$15)*0 -> 0 | D28: =(D8*'Deal Terms'!$B$14+D7*'Deal Terms'!$B$15)*'Deal Terms'!$B$17 -> 50000 | E28: =(E8*'Deal Terms'!$B$14+E7*'Deal Terms'!$B$15)*'Deal Terms'!$B$18 -> 290000 | F28: =(F8*'Deal Terms'!$B$14+F7*'Deal Terms'!$B$15)*'Deal Terms'!$B$18 -> 661000 | G28: =(G8*'Deal Terms'!$B$14+G7*'Deal Terms'!$B$15)*'Deal Terms'!$B$18 -> 1244975
A29: Royalty paid (capped) | C29: =MAX(0,MIN(C28,'Deal Terms'!$B$16*C27-0)) -> 0 | D29: =MAX(0,MIN(D28,'Deal Terms'!$B$16*D27-C30)) -> 50000 | E29: =MAX(0,MIN(E28,'Deal Terms'!$B$16*E27-D30)) -> 290000 | F29: =MAX(0,MIN(F28,'Deal Terms'!$B$16*F27-E30)) -> 661000 | G29: =MAX(0,MIN(G28,'Deal Terms'!$B$16*G27-F30)) -> 1244975
A30: Royalty paid, cumulative | C30: =0+C29 -> 0 | D30: =C30+D29 -> 50000 | E30: =D30+E29 -> 340000 | F30: =E30+F29 -> 1001000 | G30: =F30+G29 -> 2245975
A31: Tranche received (end of year) | C31: ='Deal Terms'!$B$7 -> 3000000 | D31: ='Deal Terms'!$C$7 -> 5000000 | E31: =0 -> 0 | F31: =0 -> 0 | G31: =0 -> 0
A32: CASH
A33: Y1 company costs funded outside the grant and investors | C33: =Assumptions!$B$32 -> 800000 | D33: =0 -> 0 | E33: =0 -> 0 | F33: =0 -> 0 | G33: =0 -> 0
A34: Cumulative cash with no investor money | C34: =0+C33+C24-C25-C29 -> 0 | D34: =C34+D33+D24-D25-D29 -> -2723685 | E34: =D34+E33+E24-E25-E29 -> -5814383.1 | F34: =E34+F33+F24-F25-F29 -> -7879595.8 | G34: =F34+G33+G24-G25-G29 -> -6392443.7
A35: Cash just before this year's tranche arrives | C35: =0+C33+C24-C25-C29 -> 0 | D35: =C37+D33+D24-D25-D29 -> 276315 | E35: =D37+E33+E24-E25-E29 -> 2185616.9 | F35: =E37+F33+F24-F25-F29 -> 120404.23 | G35: =F37+G33+G24-G25-G29 -> 1607556.3
A36: Bridge financing needed to stay above zero | C36: =MAX(0,-C35) -> 0 | D36: =MAX(0,-D35) -> 0 | E36: =MAX(0,-E35) -> 0 | F36: =MAX(0,-F35) -> 0 | G36: =MAX(0,-G35) -> 0
A37: Cumulative cash after tranche and bridge | C37: =C35+C31+C36 -> 3000000 | D37: =D35+D31+D36 -> 5276315 | E37: =E35+E31+E36 -> 2185616.9 | F37: =F35+F31+F36 -> 120404.23 | G37: =G35+G31+G36 -> 1607556.3
A38: INVESTOR OWNERSHIP
A39: Bridge financing, cumulative | C39: =0+C36 -> 0 | D39: =C39+D36 -> 0 | E39: =D39+E36 -> 0 | F39: =E39+F36 -> 0 | G39: =F39+G36 -> 0
A40: Investor ownership at exit (after later round and bridge) | C40: ='Deal Terms'!$B$11*(1-C39/('Deal Terms'!$C$8+C39)) -> 0.098133333 | D40: ='Deal Terms'!$B$11*(1-D39/('Deal Terms'!$C$8+D39)) -> 0.098133333 | E40: ='Deal Terms'!$B$11*(1-E39/('Deal Terms'!$C$8+E39)) -> 0.098133333 | F40: ='Deal Terms'!$B$11*(1-F39/('Deal Terms'!$C$8+F39)) -> 0.098133333 | G40: ='Deal Terms'!$B$11*(1-G39/('Deal Terms'!$C$8+G39)) -> 0.098133333
A42: BASE CASE
C43: Y1 (DOST pilot) | D43: Y2 | E43: Y3 | F43: Y4 | G43: Y5
A44: New paying municipalities | B44: =Assumptions!$B$42 -> 1 | C44: =ROUND(Assumptions!C$35*Assumptions!$B$42,0) -> 0 | D44: =ROUND(Assumptions!D$35*Assumptions!$B$42,0) -> 3 | E44: =ROUND(Assumptions!E$35*Assumptions!$B$42,0) -> 8 | F44: =ROUND(Assumptions!F$35*Assumptions!$B$42,0) -> 15 | G44: =ROUND(Assumptions!G$35*Assumptions!$B$42,0) -> 25
A45: Active paying municipalities | C45: =C44 -> 0 | D45: =C45*(1-Assumptions!$B$30)+D44 -> 3 | E45: =D45*(1-Assumptions!$B$30)+E44 -> 10.7 | F45: =E45*(1-Assumptions!$B$30)+F44 -> 24.63 | G45: =F45*(1-Assumptions!$B$30)+G44 -> 47.167
A46: Boat pods sold | C46: =0 -> 0 | D46: =ROUND(D45*Assumptions!$B$29,0) -> 150 | E46: =ROUND(E45*Assumptions!$B$29,0) -> 535 | F46: =ROUND(F45*Assumptions!$B$29,0) -> 1232 | G46: =ROUND(G45*Assumptions!$B$29,0) -> 2358
A47: Active boat pods | C47: =C46 -> 0 | D47: =C47+D46 -> 150 | E47: =D47+E46 -> 685 | F47: =E47+F46 -> 1917 | G47: =F47+G46 -> 4275
A48: REVENUE
A49: LGU subscriptions | C49: =C45*Assumptions!$B$23 -> 0 | D49: =D45*Assumptions!$B$23 -> 1050000 | E49: =E45*Assumptions!$B$23 -> 3745000 | F49: =F45*Assumptions!$B$23 -> 8620500 | G49: =G45*Assumptions!$B$23 -> 16508450
A50: Boat pod sales | C50: =C46*Assumptions!$B$24 -> 0 | D50: =D46*Assumptions!$B$24 -> 2985000 | E50: =E46*Assumptions!$B$24 -> 10646500 | F50: =F46*Assumptions!$B$24 -> 24516800 | G50: =G46*Assumptions!$B$24 -> 46924200
A51: Pod service fees | C51: =C47*Assumptions!$B$25 -> 0 | D51: =D47*Assumptions!$B$25 -> 180000 | E51: =E47*Assumptions!$B$25 -> 822000 | F51: =F47*Assumptions!$B$25 -> 2300400 | G51: =G47*Assumptions!$B$25 -> 5130000
A52: Local sponsorships | C52: =C45*Assumptions!$B$26 -> 0 | D52: =D45*Assumptions!$B$26 -> 180000 | E52: =E45*Assumptions!$B$26 -> 642000 | F52: =F45*Assumptions!$B$26 -> 1477800 | G52: =G45*Assumptions!$B$26 -> 2830020
A53: Total revenue | C53: =SUM(C49:C52) -> 0 | D53: =SUM(D49:D52) -> 4395000 | E53: =SUM(E49:E52) -> 15855500 | F53: =SUM(F49:F52) -> 36915500 | G53: =SUM(G49:G52) -> 71392670
A54: COSTS
A55: Recurring cost of active municipalities | C55: =C45*Assumptions!$B$17 -> 0 | D55: =D45*Assumptions!$B$17 -> 270000 | E55: =E45*Assumptions!$B$17 -> 963000 | F55: =F45*Assumptions!$B$17 -> 2216700 | G55: =G45*Assumptions!$B$17 -> 4245030
A56: Cost of pods sold | C56: =C46*Assumptions!$B$16*(1-Assumptions!$B$21)^0 -> 0 | D56: =D46*Assumptions!$B$16*(1-Assumptions!$B$21)^1 -> 2310000 | E56: =E46*Assumptions!$B$16*(1-Assumptions!$B$21)^2 -> 7250320 | F56: =F46*Assumptions!$B$16*(1-Assumptions!$B$21)^3 -> 14692536 | G56: =G46*Assumptions!$B$16*(1-Assumptions!$B$21)^4 -> 24746429
A57: Pod service cost | C57: =C47*(Assumptions!$B$18+Assumptions!$B$19*Assumptions!$B$16*(1-Assumptions!$B$21)^0) -> 0 | D57: =D47*(Assumptions!$B$18+Assumptions!$B$19*Assumptions!$B$16*(1-Assumptions!$B$21)^1) -> 160500 | E57: =E47*(Assumptions!$B$18+Assumptions!$B$19*Assumptions!$B$16*(1-Assumptions!$B$21)^2) -> 669656 | F57: =F47*(Assumptions!$B$18+Assumptions!$B$19*Assumptions!$B$16*(1-Assumptions!$B$21)^3) -> 1718184.1 | G57: =G47*(Assumptions!$B$18+Assumptions!$B$19*Assumptions!$B$16*(1-Assumptions!$B$21)^4) -> 3525735.5
A58: Sponsorship sales cost | C58: =C52*Assumptions!$B$27 -> 0 | D58: =D52*Assumptions!$B$27 -> 27000 | E58: =E52*Assumptions!$B$27 -> 96300 | F58: =F52*Assumptions!$B$27 -> 221670 | G58: =G52*Assumptions!$B$27 -> 424503
A59: Gross profit | C59: =C53-SUM(C55:C58) -> 0 | D59: =D53-SUM(D55:D58) -> 1627500 | E59: =E53-SUM(E55:E58) -> 6876224 | F59: =F53-SUM(F55:F58) -> 18066410 | G59: =G53-SUM(G55:G58) -> 38450973
A60: Gross margin | C60: =IF(C53=0,0,C59/C53) -> 0 | D60: =IF(D53=0,0,D59/D53) -> 0.37030717 | E60: =IF(E53=0,0,E59/E53) -> 0.43368068 | F60: =IF(F53=0,0,F59/F53) -> 0.48939902 | G60: =IF(G53=0,0,G59/G53) -> 0.53858432
A61: Company fixed costs | C61: =Assumptions!C$36 -> 800000 | D61: =Assumptions!D$36*(0.8+0.2*Assumptions!$B$42) -> 3500000 | E61: =Assumptions!E$36*(0.8+0.2*Assumptions!$B$42) -> 6000000 | F61: =Assumptions!F$36*(0.8+0.2*Assumptions!$B$42) -> 10000000 | G61: =Assumptions!G$36*(0.8+0.2*Assumptions!$B$42) -> 16000000
A62: EBITDA | C62: =C59-C61 -> -800000 | D62: =D59-D61 -> -1872500 | E62: =E59-E61 -> 876224 | F62: =F59-F61 -> 8066409.6 | G62: =G59-G61 -> 22450973
A63: Equipment for new municipalities (company-owned, leased) | C63: =C44*(Assumptions!$B$11*Assumptions!$B$12+Assumptions!$B$13*Assumptions!$B$14+Assumptions!$B$15)*(1-Assumptions!$B$20)^0 -> 0 | D63: =D44*(Assumptions!$B$11*Assumptions!$B$12+Assumptions!$B$13*Assumptions!$B$14+Assumptions!$B$15)*(1-Assumptions!$B$20)^1 -> 913027.5 | E63: =E44*(Assumptions!$B$11*Assumptions!$B$12+Assumptions!$B$13*Assumptions!$B$14+Assumptions!$B$15)*(1-Assumptions!$B$20)^2 -> 2264308.2 | F63: =F44*(Assumptions!$B$11*Assumptions!$B$12+Assumptions!$B$13*Assumptions!$B$14+Assumptions!$B$15)*(1-Assumptions!$B$20)^3 -> 3948387.4 | G63: =G44*(Assumptions!$B$11*Assumptions!$B$12+Assumptions!$B$13*Assumptions!$B$14+Assumptions!$B$15)*(1-Assumptions!$B$20)^4 -> 6120000.5
A64: INVESTOR
A65: Investor money paid in, cumulative (start of year) | C65: =0 -> 0 | D65: ='Deal Terms'!$B$7 -> 3000000 | E65: ='Deal Terms'!$B$7+'Deal Terms'!$C$7 -> 8000000 | F65: ='Deal Terms'!$B$7+'Deal Terms'!$C$7 -> 8000000 | G65: ='Deal Terms'!$B$7+'Deal Terms'!$C$7 -> 8000000
A66: Royalty earned at tranche-based rates | C66: =(C46*'Deal Terms'!$B$14+C45*'Deal Terms'!$B$15)*0 -> 0 | D66: =(D46*'Deal Terms'!$B$14+D45*'Deal Terms'!$B$15)*'Deal Terms'!$B$17 -> 75000 | E66: =(E46*'Deal Terms'!$B$14+E45*'Deal Terms'!$B$15)*'Deal Terms'!$B$18 -> 535000 | F66: =(F46*'Deal Terms'!$B$14+F45*'Deal Terms'!$B$15)*'Deal Terms'!$B$18 -> 1231875 | G66: =(G46*'Deal Terms'!$B$14+G45*'Deal Terms'!$B$15)*'Deal Terms'!$B$18 -> 2358087.5
A67: Royalty paid (capped) | C67: =MAX(0,MIN(C66,'Deal Terms'!$B$16*C65-0)) -> 0 | D67: =MAX(0,MIN(D66,'Deal Terms'!$B$16*D65-C68)) -> 75000 | E67: =MAX(0,MIN(E66,'Deal Terms'!$B$16*E65-D68)) -> 535000 | F67: =MAX(0,MIN(F66,'Deal Terms'!$B$16*F65-E68)) -> 1231875 | G67: =MAX(0,MIN(G66,'Deal Terms'!$B$16*G65-F68)) -> 2358087.5
A68: Royalty paid, cumulative | C68: =0+C67 -> 0 | D68: =C68+D67 -> 75000 | E68: =D68+E67 -> 610000 | F68: =E68+F67 -> 1841875 | G68: =F68+G67 -> 4199962.5
A69: Tranche received (end of year) | C69: ='Deal Terms'!$B$7 -> 3000000 | D69: ='Deal Terms'!$C$7 -> 5000000 | E69: =0 -> 0 | F69: =0 -> 0 | G69: =0 -> 0
A70: CASH
A71: Y1 company costs funded outside the grant and investors | C71: =Assumptions!$B$32 -> 800000 | D71: =0 -> 0 | E71: =0 -> 0 | F71: =0 -> 0 | G71: =0 -> 0
A72: Cumulative cash with no investor money | C72: =0+C71+C62-C63-C67 -> 0 | D72: =C72+D71+D62-D63-D67 -> -2860527.5 | E72: =D72+E71+E62-E63-E67 -> -4783611.7 | F72: =E72+F71+F62-F63-F67 -> -1897464.5 | G72: =F72+G71+G62-G63-G67 -> 12075420
A73: Cash just before this year's tranche arrives | C73: =0+C71+C62-C63-C67 -> 0 | D73: =C75+D71+D62-D63-D67 -> 139472.5 | E73: =D75+E71+E62-E63-E67 -> 3216388.3 | F73: =E75+F71+F62-F63-F67 -> 6102535.5 | G73: =F75+G71+G62-G63-G67 -> 20075420
A74: Bridge financing needed to stay above zero | C74: =MAX(0,-C73) -> 0 | D74: =MAX(0,-D73) -> 0 | E74: =MAX(0,-E73) -> 0 | F74: =MAX(0,-F73) -> 0 | G74: =MAX(0,-G73) -> 0
A75: Cumulative cash after tranche and bridge | C75: =C73+C69+C74 -> 3000000 | D75: =D73+D69+D74 -> 5139472.5 | E75: =E73+E69+E74 -> 3216388.3 | F75: =F73+F69+F74 -> 6102535.5 | G75: =G73+G69+G74 -> 20075420
A76: INVESTOR OWNERSHIP
A77: Bridge financing, cumulative | C77: =0+C74 -> 0 | D77: =C77+D74 -> 0 | E77: =D77+E74 -> 0 | F77: =E77+F74 -> 0 | G77: =F77+G74 -> 0
A78: Investor ownership at exit (after later round and bridge) | C78: ='Deal Terms'!$B$11*(1-C77/('Deal Terms'!$C$8+C77)) -> 0.098133333 | D78: ='Deal Terms'!$B$11*(1-D77/('Deal Terms'!$C$8+D77)) -> 0.098133333 | E78: ='Deal Terms'!$B$11*(1-E77/('Deal Terms'!$C$8+E77)) -> 0.098133333 | F78: ='Deal Terms'!$B$11*(1-F77/('Deal Terms'!$C$8+F77)) -> 0.098133333 | G78: ='Deal Terms'!$B$11*(1-G77/('Deal Terms'!$C$8+G77)) -> 0.098133333
A80: HIGH CASE
C81: Y1 (DOST pilot) | D81: Y2 | E81: Y3 | F81: Y4 | G81: Y5
A82: New paying municipalities | B82: =Assumptions!$B$43 -> 1.6 | C82: =ROUND(Assumptions!C$35*Assumptions!$B$43,0) -> 0 | D82: =ROUND(Assumptions!D$35*Assumptions!$B$43,0) -> 5 | E82: =ROUND(Assumptions!E$35*Assumptions!$B$43,0) -> 13 | F82: =ROUND(Assumptions!F$35*Assumptions!$B$43,0) -> 24 | G82: =ROUND(Assumptions!G$35*Assumptions!$B$43,0) -> 40
A83: Active paying municipalities | C83: =C82 -> 0 | D83: =C83*(1-Assumptions!$B$30)+D82 -> 5 | E83: =D83*(1-Assumptions!$B$30)+E82 -> 17.5 | F83: =E83*(1-Assumptions!$B$30)+F82 -> 39.75 | G83: =F83*(1-Assumptions!$B$30)+G82 -> 75.775
A84: Boat pods sold | C84: =0 -> 0 | D84: =ROUND(D83*Assumptions!$B$29,0) -> 250 | E84: =ROUND(E83*Assumptions!$B$29,0) -> 875 | F84: =ROUND(F83*Assumptions!$B$29,0) -> 1988 | G84: =ROUND(G83*Assumptions!$B$29,0) -> 3789
A85: Active boat pods | C85: =C84 -> 0 | D85: =C85+D84 -> 250 | E85: =D85+E84 -> 1125 | F85: =E85+F84 -> 3113 | G85: =F85+G84 -> 6902
A86: REVENUE
A87: LGU subscriptions | C87: =C83*Assumptions!$B$23 -> 0 | D87: =D83*Assumptions!$B$23 -> 1750000 | E87: =E83*Assumptions!$B$23 -> 6125000 | F87: =F83*Assumptions!$B$23 -> 13912500 | G87: =G83*Assumptions!$B$23 -> 26521250
A88: Boat pod sales | C88: =C84*Assumptions!$B$24 -> 0 | D88: =D84*Assumptions!$B$24 -> 4975000 | E88: =E84*Assumptions!$B$24 -> 17412500 | F88: =F84*Assumptions!$B$24 -> 39561200 | G88: =G84*Assumptions!$B$24 -> 75401100
A89: Pod service fees | C89: =C85*Assumptions!$B$25 -> 0 | D89: =D85*Assumptions!$B$25 -> 300000 | E89: =E85*Assumptions!$B$25 -> 1350000 | F89: =F85*Assumptions!$B$25 -> 3735600 | G89: =G85*Assumptions!$B$25 -> 8282400
A90: Local sponsorships | C90: =C83*Assumptions!$B$26 -> 0 | D90: =D83*Assumptions!$B$26 -> 300000 | E90: =E83*Assumptions!$B$26 -> 1050000 | F90: =F83*Assumptions!$B$26 -> 2385000 | G90: =G83*Assumptions!$B$26 -> 4546500
A91: Total revenue | C91: =SUM(C87:C90) -> 0 | D91: =SUM(D87:D90) -> 7325000 | E91: =SUM(E87:E90) -> 25937500 | F91: =SUM(F87:F90) -> 59594300 | G91: =SUM(G87:G90) -> 114751250
A92: COSTS
A93: Recurring cost of active municipalities | C93: =C83*Assumptions!$B$17 -> 0 | D93: =D83*Assumptions!$B$17 -> 450000 | E93: =E83*Assumptions!$B$17 -> 1575000 | F93: =F83*Assumptions!$B$17 -> 3577500 | G93: =G83*Assumptions!$B$17 -> 6819750
A94: Cost of pods sold | C94: =C84*Assumptions!$B$16*(1-Assumptions!$B$21)^0 -> 0 | D94: =D84*Assumptions!$B$16*(1-Assumptions!$B$21)^1 -> 3850000 | E94: =E84*Assumptions!$B$16*(1-Assumptions!$B$21)^2 -> 11858000 | F94: =F84*Assumptions!$B$16*(1-Assumptions!$B$21)^3 -> 23708411 | G94: =G84*Assumptions!$B$16*(1-Assumptions!$B$21)^4 -> 39764300
A95: Pod service cost | C95: =C85*(Assumptions!$B$18+Assumptions!$B$19*Assumptions!$B$16*(1-Assumptions!$B$21)^0) -> 0 | D95: =D85*(Assumptions!$B$18+Assumptions!$B$19*Assumptions!$B$16*(1-Assumptions!$B$21)^1) -> 267500 | E95: =E85*(Assumptions!$B$18+Assumptions!$B$19*Assumptions!$B$16*(1-Assumptions!$B$21)^2) -> 1099800 | F95: =F85*(Assumptions!$B$18+Assumptions!$B$19*Assumptions!$B$16*(1-Assumptions!$B$21)^3) -> 2790144.5 | G95: =G85*(Assumptions!$B$18+Assumptions!$B$19*Assumptions!$B$16*(1-Assumptions!$B$21)^4) -> 5692310.2
A96: Sponsorship sales cost | C96: =C90*Assumptions!$B$27 -> 0 | D96: =D90*Assumptions!$B$27 -> 45000 | E96: =E90*Assumptions!$B$27 -> 157500 | F96: =F90*Assumptions!$B$27 -> 357750 | G96: =G90*Assumptions!$B$27 -> 681975
A97: Gross profit | C97: =C91-SUM(C93:C96) -> 0 | D97: =D91-SUM(D93:D96) -> 2712500 | E97: =E91-SUM(E93:E96) -> 11247200 | F97: =F91-SUM(F93:F96) -> 29160495 | G97: =G91-SUM(G93:G96) -> 61792915
A98: Gross margin | C98: =IF(C91=0,0,C97/C91) -> 0 | D98: =IF(D91=0,0,D97/D91) -> 0.37030717 | E98: =IF(E91=0,0,E97/E91) -> 0.43362699 | F98: =IF(F91=0,0,F97/F91) -> 0.48931684 | G98: =IF(G91=0,0,G97/G91) -> 0.53849448
A99: Company fixed costs | C99: =Assumptions!C$36 -> 800000 | D99: =Assumptions!D$36*(0.8+0.2*Assumptions!$B$43) -> 3920000 | E99: =Assumptions!E$36*(0.8+0.2*Assumptions!$B$43) -> 6720000 | F99: =Assumptions!F$36*(0.8+0.2*Assumptions!$B$43) -> 11200000 | G99: =Assumptions!G$36*(0.8+0.2*Assumptions!$B$43) -> 17920000
A100: EBITDA | C100: =C97-C99 -> -800000 | D100: =D97-D99 -> -1207500 | E100: =E97-E99 -> 4527200 | F100: =F97-F99 -> 17960495 | G100: =G97-G99 -> 43872915
A101: Equipment for new municipalities (company-owned, leased) | C101: =C82*(Assumptions!$B$11*Assumptions!$B$12+Assumptions!$B$13*Assumptions!$B$14+Assumptions!$B$15)*(1-Assumptions!$B$20)^0 -> 0 | D101: =D82*(Assumptions!$B$11*Assumptions!$B$12+Assumptions!$B$13*Assumptions!$B$14+Assumptions!$B$15)*(1-Assumptions!$B$20)^1 -> 1521712.5 | E101: =E82*(Assumptions!$B$11*Assumptions!$B$12+Assumptions!$B$13*Assumptions!$B$14+Assumptions!$B$15)*(1-Assumptions!$B$20)^2 -> 3679500.8 | F101: =F82*(Assumptions!$B$11*Assumptions!$B$12+Assumptions!$B$13*Assumptions!$B$14+Assumptions!$B$15)*(1-Assumptions!$B$20)^3 -> 6317419.9 | G101: =G82*(Assumptions!$B$11*Assumptions!$B$12+Assumptions!$B$13*Assumptions!$B$14+Assumptions!$B$15)*(1-Assumptions!$B$20)^4 -> 9792000.8
A102: INVESTOR
A103: Investor money paid in, cumulative (start of year) | C103: =0 -> 0 | D103: ='Deal Terms'!$B$7 -> 3000000 | E103: ='Deal Terms'!$B$7+'Deal Terms'!$C$7 -> 8000000 | F103: ='Deal Terms'!$B$7+'Deal Terms'!$C$7 -> 8000000 | G103: ='Deal Terms'!$B$7+'Deal Terms'!$C$7 -> 8000000
...

Sheet Investor Returns
A1: AqOne Investor Returns - Hybrid, Tranched
A2: Cash flows to the investor at each year end. Negative = money in; positive = royalties and the equity value at exit (end of Y5).
A4: LOW CASE
C5: Y1 (DOST pilot) | D5: Y2 | E5: Y3 | F5: Y4 | G5: Y5
A6: Tranche paid in | C6: =-Projections!C31 -> -3000000 | D6: =-Projections!D31 -> -5000000 | E6: =-Projections!E31 -> 0 | F6: =-Projections!F31 -> 0 | G6: =-Projections!G31 -> 0
A7: Royalty received | C7: =Projections!C29 -> 0 | D7: =Projections!D29 -> 50000 | E7: =Projections!E29 -> 290000 | F7: =Projections!F29 -> 661000 | G7: =Projections!G29 -> 1244975
A8: Equity value at exit | C8: =0 -> 0 | D8: =0 -> 0 | E8: =0 -> 0 | F8: =0 -> 0 | G8: =Projections!G15*Assumptions!$C$41*Projections!G40 -> 7406884.2
A9: Net cash flow to investor | C9: =SUM(C6:C8) -> -3000000 | D9: =SUM(D6:D8) -> -4950000 | E9: =SUM(E6:E8) -> 290000 | F9: =SUM(F6:F8) -> 661000 | G9: =SUM(G6:G8) -> 8651859.2
A11: Total paid in | B11: =-SUM(C6:G6) -> 8000000
A12: Total royalties received by Y5 | B12: =SUM(C7:G7) -> 2245975
A13: Equity value at exit (Y5 revenue × multiple × ownership) | B13: =G8 -> 7406884.2
A14: Money multiple (total received ÷ paid in) | B14: =(B12+B13)/B11 -> 1.2066074
A15: Annualized return (IRR) | B15: =IRR(C9:G9) -> 0.059845203
A16: Royalties repay 100% of money paid in | B16: =IF(B12>=B11-1,"By Y5","After Y5") -> After Y5
A17: Money multiple with no exit (royalties only, by Y5) | B17: =B12/B11 -> 0.28074688
A18: Net cash flow to investor with no exit | C18: =C6+C7 -> -3000000 | D18: =D6+D7 -> -4950000 | E18: =E6+E7 -> 290000 | F18: =F6+F7 -> 661000 | G18: =G6+G7 -> 1244975
A19: Annualized return with no exit (IRR) | B19: =IFERROR(IRR(C18:G18,-0.2),"n/a") -> -0.36173008
A21: BASE CASE
C22: Y1 (DOST pilot) | D22: Y2 | E22: Y3 | F22: Y4 | G22: Y5
A23: Tranche paid in | C23: =-Projections!C69 -> -3000000 | D23: =-Projections!D69 -> -5000000 | E23: =-Projections!E69 -> 0 | F23: =-Projections!F69 -> 0 | G23: =-Projections!G69 -> 0
A24: Royalty received | C24: =Projections!C67 -> 0 | D24: =Projections!D67 -> 75000 | E24: =Projections!E67 -> 535000 | F24: =Projections!F67 -> 1231875 | G24: =Projections!G67 -> 2358087.5
A25: Equity value at exit | C25: =0 -> 0 | D25: =0 -> 0 | E25: =0 -> 0 | F25: =0 -> 0 | G25: =Projections!G53*Assumptions!$C$42*Projections!G78 -> 21018002
A26: Net cash flow to investor | C26: =SUM(C23:C25) -> -3000000 | D26: =SUM(D23:D25) -> -4925000 | E26: =SUM(E23:E25) -> 535000 | F26: =SUM(F23:F25) -> 1231875 | G26: =SUM(G23:G25) -> 23376090
A28: Total paid in | B28: =-SUM(C23:G23) -> 8000000
A29: Total royalties received by Y5 | B29: =SUM(C24:G24) -> 4199962.5
A30: Equity value at exit (Y5 revenue × multiple × ownership) | B30: =G25 -> 21018002
A31: Money multiple (total received ÷ paid in) | B31: =(B29+B30)/B28 -> 3.1522456
A32: Annualized return (IRR) | B32: =IRR(C26:G26) -> 0.41844772
A33: Royalties repay 100% of money paid in | B33: =IF(B29>=B28-1,"By Y5","After Y5") -> After Y5
A34: Money multiple with no exit (royalties only, by Y5) | B34: =B29/B28 -> 0.52499531
A35: Net cash flow to investor with no exit | C35: =C23+C24 -> -3000000 | D35: =D23+D24 -> -4925000 | E35: =E23+E24 -> 535000 | F35: =F23+F24 -> 1231875 | G35: =G23+G24 -> 2358087.5
A36: Annualized return with no exit (IRR) | B36: =IFERROR(IRR(C35:G35,-0.2),"n/a") -> -0.20480588
A38: HIGH CASE
C39: Y1 (DOST pilot) | D39: Y2 | E39: Y3 | F39: Y4 | G39: Y5
A40: Tranche paid in | C40: =-Projections!C107 -> -3000000 | D40: =-Projections!D107 -> -5000000 | E40: =-Projections!E107 -> 0 | F40: =-Projections!F107 -> 0 | G40: =-Projections!G107 -> 0
A41: Royalty received | C41: =Projections!C105 -> 0 | D41: =Projections!D105 -> 125000 | E41: =Projections!E105 -> 875000 | F41: =Projections!F105 -> 1987875 | G41: =Projections!G105 -> 3788937.5
A42: Equity value at exit | C42: =0 -> 0 | D42: =0 -> 0 | E42: =0 -> 0 | F42: =0 -> 0 | G42: =Projections!G91*Assumptions!$C$43*Projections!G116 -> 45043691
A43: Net cash flow to investor | C43: =SUM(C40:C42) -> -3000000 | D43: =SUM(D40:D42) -> -4875000 | E43: =SUM(E40:E42) -> 875000 | F43: =SUM(F40:F42) -> 1987875 | G43: =SUM(G40:G42) -> 48832628
A45: Total paid in | B45: =-SUM(C40:G40) -> 8000000
A46: Total royalties received by Y5 | B46: =SUM(C41:G41) -> 6776812.5
A47: Equity value at exit (Y5 revenue × multiple × ownership) | B47: =G42 -> 45043691
A48: Money multiple (total received ÷ paid in) | B48: =(B46+B47)/B45 -> 6.4775629
A49: Annualized return (IRR) | B49: =IRR(C43:G43) -> 0.75695384
A50: Royalties repay 100% of money paid in | B50: =IF(B46>=B45-1,"By Y5","After Y5") -> After Y5
A51: Money multiple with no exit (royalties only, by Y5) | B51: =B46/B45 -> 0.84710156
A52: Net cash flow to investor with no exit | C52: =C40+C41 -> -3000000 | D52: =D40+D41 -> -4875000 | E52: =E40+E41 -> 875000 | F52: =F40+F41 -> 1987875 | G52: =G40+G41 -> 3788937.5
A53: Annualized return with no exit (IRR) | B53: =IFERROR(IRR(C52:G52,-0.2),"n/a") -> -0.057962974
